Workbook

Sheet MarketplaceFees
A1: [MarketplaceFees Assumptions] | C1: Inputs used by the marketplace fee projection below.
A2: name | B2: value | C2: details
A3: projection_start_month | B3: 2026-03 | C3: First month of the synthetic projection in YYYY-MM format.
A4: seasonality_lookback_years | B4: 10 | C4: Historical lookback window used to build month-level seasonality factors.
A5: baseline_month | B5: 2026-03-01 | C5: Observed marketplace month used to anchor GMV and average selling price.
A6: baseline_month_gmv_usd | B6: 2165763 | C6: Observed GMV for the baseline month from raw daily sales data.
A7: baseline_month_transaction_count | B7: 514 | C7: Observed transaction count for the baseline month from raw daily sales data.
A8: baseline_month_avg_sell_price_usd | B8: 4213.55 | C8: Derived average selling price for the baseline month.
A9: sales_cagr | B9: 0.03 | C9: Annual growth rate applied to marketplace sales in Years 2 and 3.
A10: avg_sell_price_annual_growth | B10: 0.03 | C10: Annual inflation-style growth rate applied to average selling price.
A11: take_rate | B11: 0.02 | C11: Marketplace fee rate applied to projected GMV.
A12: year2_3_min_txns | B12: 10 | C12: Lower bound for projected monthly transaction count after Year 1.
A13: year2_3_max_txns | B13: 400 | C13: Upper bound for projected monthly transaction count after Year 1.
A14: jitter_std | B14: 0.05 | C14: Standard deviation used by the random-driver formulas.
A16: month | B16: year_index | C16: phase | D16: seasonality_factor | E16: noise_market_year1_jitter | F16: noise_market_txn | G16: noise_market_avg_sell_price | H16: cagr_multiplier | I16: noise_market_combined | J16: txn_trend_base | K16: txn_seasonality_multiplier | L16: transaction_count | M16: avg_sell_price_growth | N16: avg_sell_price_usd | O16: gross_market_value_usd | P16: take_rate | Q16: transaction_fee_revenue_usd
A17: 2026-03-01 | B17: 1 | C17: phase_1_user_growth | D17: 1 | E17: =MAX(0.7,1+_xlfn.NORM.INV(RAND(),0,$B$14*0.5)) -> 0.996398 | F17: =MAX(0.85,1+_xlfn.NORM.INV(RAND(),0,$B$14*0.4)) -> 1 | G17: =MAX(0.75,1+_xlfn.NORM.INV(RAND(),0,$B$14*0.35)) -> 1 | H17: =IF($B17=1,1,POWER(1+$B$9,-12/12)) -> 1 | I17: =IF($B17=1,E17,F17*G17) -> 0.996398 | J17: =IF($B17=1,0,$B$12+($B$13-$B$12)*(-12/23)) -> 0 | K17: =IF($B17=1,0,0.85+0.15*D17) -> 0 | L17: =IF($B17=1,0,MIN($B$13,MAX($B$12,ROUND(J17*K17*F17,0)))) -> 0 | M17: =IF($B17=1,0,1+($B$10*-12/12)) -> 0 | N17: =IF($B17=1,0,ROUND($B$8*M17*G17,2)) -> 0 | O17: =ROUND(L17*N17,2) -> 0 | P17: =$B$11 -> 0.02 | Q17: =ROUND(IF(L17>0,O17*P17,0),2) -> 0
A18: 2026-04-01 | B18: 1 | C18: phase_1_user_growth | D18: 0.98994723 | E18: =MAX(0.7,1+_xlfn.NORM.INV(RAND(),0,$B$14*0.5)) -> 0.995677 | F18: =MAX(0.85,1+_xlfn.NORM.INV(RAND(),0,$B$14*0.4)) -> 1 | G18: =MAX(0.75,1+_xlfn.NORM.INV(RAND(),0,$B$14*0.35)) -> 1 | H18: =IF($B18=1,1,POWER(1+$B$9,-11/12)) -> 1 | I18: =IF($B18=1,E18,F18*G18) -> 0.995677 | J18: =IF($B18=1,0,$B$12+($B$13-$B$12)*(-11/23)) -> 0 | K18: =IF($B18=1,0,0.85+0.15*D18) -> 0 | L18: =IF($B18=1,0,MIN($B$13,MAX($B$12,ROUND(J18*K18*F18,0)))) -> 0 | M18: =IF($B18=1,0,1+($B$10*-11/12)) -> 0 | N18: =IF($B18=1,0,ROUND($B$8*M18*G18,2)) -> 0 | O18: =ROUND(L18*N18,2) -> 0 | P18: =$B$11 -> 0.02 | Q18: =ROUND(IF(L18>0,O18*P18,0),2) -> 0
A19: 2026-05-01 | B19: 1 | C19: phase_1_user_growth | D19: 1.1889394 | E19: =MAX(0.7,1+_xlfn.NORM.INV(RAND(),0,$B$14*0.5)) -> 0.997217 | F19: =MAX(0.85,1+_xlfn.NORM.INV(RAND(),0,$B$14*0.4)) -> 1 | G19: =MAX(0.75,1+_xlfn.NORM.INV(RAND(),0,$B$14*0.35)) -> 1 | H19: =IF($B19=1,1,POWER(1+$B$9,-10/12)) -> 1 | I19: =IF($B19=1,E19,F19*G19) -> 0.997217 | J19: =IF($B19=1,0,$B$12+($B$13-$B$12)*(-10/23)) -> 0 | K19: =IF($B19=1,0,0.85+0.15*D19) -> 0 | L19: =IF($B19=1,0,MIN($B$13,MAX($B$12,ROUND(J19*K19*F19,0)))) -> 0 | M19: =IF($B19=1,0,1+($B$10*-10/12)) -> 0 | N19: =IF($B19=1,0,ROUND($B$8*M19*G19,2)) -> 0 | O19: =ROUND(L19*N19,2) -> 0 | P19: =$B$11 -> 0.02 | Q19: =ROUND(IF(L19>0,O19*P19,0),2) -> 0
A20: 2026-06-01 | B20: 1 | C20: phase_1_user_growth | D20: 1.0635797 | E20: =MAX(0.7,1+_xlfn.NORM.INV(RAND(),0,$B$14*0.5)) -> 1.01755 | F20: =MAX(0.85,1+_xlfn.NORM.INV(RAND(),0,$B$14*0.4)) -> 1 | G20: =MAX(0.75,1+_xlfn.NORM.INV(RAND(),0,$B$14*0.35)) -> 1 | H20: =IF($B20=1,1,POWER(1+$B$9,-9/12)) -> 1 | I20: =IF($B20=1,E20,F20*G20) -> 1.01755 | J20: =IF($B20=1,0,$B$12+($B$13-$B$12)*(-9/23)) -> 0 | K20: =IF($B20=1,0,0.85+0.15*D20) -> 0 | L20: =IF($B20=1,0,MIN($B$13,MAX($B$12,ROUND(J20*K20*F20,0)))) -> 0 | M20: =IF($B20=1,0,1+($B$10*-9/12)) -> 0 | N20: =IF($B20=1,0,ROUND($B$8*M20*G20,2)) -> 0 | O20: =ROUND(L20*N20,2) -> 0 | P20: =$B$11 -> 0.02 | Q20: =ROUND(IF(L20>0,O20*P20,0),2) -> 0
A21: 2026-07-01 | B21: 1 | C21: phase_1_user_growth | D21: 1.0466681 | E21: =MAX(0.7,1+_xlfn.NORM.INV(RAND(),0,$B$14*0.5)) -> 0.99681 | F21: =MAX(0.85,1+_xlfn.NORM.INV(RAND(),0,$B$14*0.4)) -> 1 | G21: =MAX(0.75,1+_xlfn.NORM.INV(RAND(),0,$B$14*0.35)) -> 1 | H21: =IF($B21=1,1,POWER(1+$B$9,-8/12)) -> 1 | I21: =IF($B21=1,E21,F21*G21) -> 0.99681 | J21: =IF($B21=1,0,$B$12+($B$13-$B$12)*(-8/23)) -> 0 | K21: =IF($B21=1,0,0.85+0.15*D21) -> 0 | L21: =IF($B21=1,0,MIN($B$13,MAX($B$12,ROUND(J21*K21*F21,0)))) -> 0 | M21: =IF($B21=1,0,1+($B$10*-8/12)) -> 0 | N21: =IF($B21=1,0,ROUND($B$8*M21*G21,2)) -> 0 | O21: =ROUND(L21*N21,2) -> 0 | P21: =$B$11 -> 0.02 | Q21: =ROUND(IF(L21>0,O21*P21,0),2) -> 0
A22: 2026-08-01 | B22: 1 | C22: phase_1_user_growth | D22: 1.0816408 | E22: =MAX(0.7,1+_xlfn.NORM.INV(RAND(),0,$B$14*0.5)) -> 0.962566 | F22: =MAX(0.85,1+_xlfn.NORM.INV(RAND(),0,$B$14*0.4)) -> 1 | G22: =MAX(0.75,1+_xlfn.NORM.INV(RAND(),0,$B$14*0.35)) -> 1 | H22: =IF($B22=1,1,POWER(1+$B$9,-7/12)) -> 1 | I22: =IF($B22=1,E22,F22*G22) -> 0.962566 | J22: =IF($B22=1,0,$B$12+($B$13-$B$12)*(-7/23)) -> 0 | K22: =IF($B22=1,0,0.85+0.15*D22) -> 0 | L22: =IF($B22=1,0,MIN($B$13,MAX($B$12,ROUND(J22*K22*F22,0)))) -> 0 | M22: =IF($B22=1,0,1+($B$10*-7/12)) -> 0 | N22: =IF($B22=1,0,ROUND($B$8*M22*G22,2)) -> 0 | O22: =ROUND(L22*N22,2) -> 0 | P22: =$B$11 -> 0.02 | Q22: =ROUND(IF(L22>0,O22*P22,0),2) -> 0
A23: 2026-09-01 | B23: 1 | C23: phase_1_user_growth | D23: 1.0397956 | E23: =MAX(0.7,1+_xlfn.NORM.INV(RAND(),0,$B$14*0.5)) -> 1.008308 | F23: =MAX(0.85,1+_xlfn.NORM.INV(RAND(),0,$B$14*0.4)) -> 1 | G23: =MAX(0.75,1+_xlfn.NORM.INV(RAND(),0,$B$14*0.35)) -> 1 | H23: =IF($B23=1,1,POWER(1+$B$9,-6/12)) -> 1 | I23: =IF($B23=1,E23,F23*G23) -> 1.008308 | J23: =IF($B23=1,0,$B$12+($B$13-$B$12)*(-6/23)) -> 0 | K23: =IF($B23=1,0,0.85+0.15*D23) -> 0 | L23: =IF($B23=1,0,MIN($B$13,MAX($B$12,ROUND(J23*K23*F23,0)))) -> 0 | M23: =IF($B23=1,0,1+($B$10*-6/12)) -> 0 | N23: =IF($B23=1,0,ROUND($B$8*M23*G23,2)) -> 0 | O23: =ROUND(L23*N23,2) -> 0 | P23: =$B$11 -> 0.02 | Q23: =ROUND(IF(L23>0,O23*P23,0),2) -> 0
A24: 2026-10-01 | B24: 1 | C24: phase_1_user_growth | D24: 1.0691942 | E24: =MAX(0.7,1+_xlfn.NORM.INV(RAND(),0,$B$14*0.5)) -> 0.993317 | F24: =MAX(0.85,1+_xlfn.NORM.INV(RAND(),0,$B$14*0.4)) -> 1 | G24: =MAX(0.75,1+_xlfn.NORM.INV(RAND(),0,$B$14*0.35)) -> 1 | H24: =IF($B24=1,1,POWER(1+$B$9,-5/12)) -> 1 | I24: =IF($B24=1,E24,F24*G24) -> 0.993317 | J24: =IF($B24=1,0,$B$12+($B$13-$B$12)*(-5/23)) -> 0 | K24: =IF($B24=1,0,0.85+0.15*D24) -> 0 | L24: =IF($B24=1,0,MIN($B$13,MAX($B$12,ROUND(J24*K24*F24,0)))) -> 0 | M24: =IF($B24=1,0,1+($B$10*-5/12)) -> 0 | N24: =IF($B24=1,0,ROUND($B$8*M24*G24,2)) -> 0 | O24: =ROUND(L24*N24,2) -> 0 | P24: =$B$11 -> 0.02 | Q24: =ROUND(IF(L24>0,O24*P24,0),2) -> 0
A25: 2026-11-01 | B25: 1 | C25: phase_1_user_growth | D25: 1.213324 | E25: =MAX(0.7,1+_xlfn.NORM.INV(RAND(),0,$B$14*0.5)) -> 0.994576 | F25: =MAX(0.85,1+_xlfn.NORM.INV(RAND(),0,$B$14*0.4)) -> 1 | G25: =MAX(0.75,1+_xlfn.NORM.INV(RAND(),0,$B$14*0.35)) -> 1 | H25: =IF($B25=1,1,POWER(1+$B$9,-4/12)) -> 1 | I25: =IF($B25=1,E25,F25*G25) -> 0.994576 | J25: =IF($B25=1,0,$B$12+($B$13-$B$12)*(-4/23)) -> 0 | K25: =IF($B25=1,0,0.85+0.15*D25) -> 0 | L25: =IF($B25=1,0,MIN($B$13,MAX($B$12,ROUND(J25*K25*F25,0)))) -> 0 | M25: =IF($B25=1,0,1+($B$10*-4/12)) -> 0 | N25: =IF($B25=1,0,ROUND($B$8*M25*G25,2)) -> 0 | O25: =ROUND(L25*N25,2) -> 0 | P25: =$B$11 -> 0.02 | Q25: =ROUND(IF(L25>0,O25*P25,0),2) -> 0
A26: 2026-12-01 | B26: 1 | C26: phase_1_user_growth | D26: 2.2762742 | E26: =MAX(0.7,1+_xlfn.NORM.INV(RAND(),0,$B$14*0.5)) -> 1.002897 | F26: =MAX(0.85,1+_xlfn.NORM.INV(RAND(),0,$B$14*0.4)) -> 1 | G26: =MAX(0.75,1+_xlfn.NORM.INV(RAND(),0,$B$14*0.35)) -> 1 | H26: =IF($B26=1,1,POWER(1+$B$9,-3/12)) -> 1 | I26: =IF($B26=1,E26,F26*G26) -> 1.002897 | J26: =IF($B26=1,0,$B$12+($B$13-$B$12)*(-3/23)) -> 0 | K26: =IF($B26=1,0,0.85+0.15*D26) -> 0 | L26: =IF($B26=1,0,MIN($B$13,MAX($B$12,ROUND(J26*K26*F26,0)))) -> 0 | M26: =IF($B26=1,0,1+($B$10*-3/12)) -> 0 | N26: =IF($B26=1,0,ROUND($B$8*M26*G26,2)) -> 0 | O26: =ROUND(L26*N26,2) -> 0 | P26: =$B$11 -> 0.02 | Q26: =ROUND(IF(L26>0,O26*P26,0),2) -> 0
A27: 2027-01-01 | B27: 1 | C27: phase_1_user_growth | D27: 0.94587711 | E27: =MAX(0.7,1+_xlfn.NORM.INV(RAND(),0,$B$14*0.5)) -> 1.005807 | F27: =MAX(0.85,1+_xlfn.NORM.INV(RAND(),0,$B$14*0.4)) -> 1 | G27: =MAX(0.75,1+_xlfn.NORM.INV(RAND(),0,$B$14*0.35)) -> 1 | H27: =IF($B27=1,1,POWER(1+$B$9,-2/12)) -> 1 | I27: =IF($B27=1,E27,F27*G27) -> 1.005807 | J27: =IF($B27=1,0,$B$12+($B$13-$B$12)*(-2/23)) -> 0 | K27: =IF($B27=1,0,0.85+0.15*D27) -> 0 | L27: =IF($B27=1,0,MIN($B$13,MAX($B$12,ROUND(J27*K27*F27,0)))) -> 0 | M27: =IF($B27=1,0,1+($B$10*-2/12)) -> 0 | N27: =IF($B27=1,0,ROUND($B$8*M27*G27,2)) -> 0 | O27: =ROUND(L27*N27,2) -> 0 | P27: =$B$11 -> 0.02 | Q27: =ROUND(IF(L27>0,O27*P27,0),2) -> 0
A28: 2027-02-01 | B28: 1 | C28: phase_1_user_growth | D28: 1.167967 | E28: =MAX(0.7,1+_xlfn.NORM.INV(RAND(),0,$B$14*0.5)) -> 1.029089 | F28: =MAX(0.85,1+_xlfn.NORM.INV(RAND(),0,$B$14*0.4)) -> 1 | G28: =MAX(0.75,1+_xlfn.NORM.INV(RAND(),0,$B$14*0.35)) -> 1 | H28: =IF($B28=1,1,POWER(1+$B$9,-1/12)) -> 1 | I28: =IF($B28=1,E28,F28*G28) -> 1.029089 | J28: =IF($B28=1,0,$B$12+($B$13-$B$12)*(-1/23)) -> 0 | K28: =IF($B28=1,0,0.85+0.15*D28) -> 0 | L28: =IF($B28=1,0,MIN($B$13,MAX($B$12,ROUND(J28*K28*F28,0)))) -> 0 | M28: =IF($B28=1,0,1+($B$10*-1/12)) -> 0 | N28: =IF($B28=1,0,ROUND($B$8*M28*G28,2)) -> 0 | O28: =ROUND(L28*N28,2) -> 0 | P28: =$B$11 -> 0.02 | Q28: =ROUND(IF(L28>0,O28*P28,0),2) -> 0
A29: 2027-03-01 | B29: 2 | C29: phase_2_marketplace_activation | D29: 1 | E29: =MAX(0.7,1+_xlfn.NORM.INV(RAND(),0,$B$14*0.5)) -> 1 | F29: =MAX(0.85,1+_xlfn.NORM.INV(RAND(),0,$B$14*0.4)) -> 1.013133 | G29: =MAX(0.75,1+_xlfn.NORM.INV(RAND(),0,$B$14*0.35)) -> 1.001934 | H29: =IF($B29=1,1,POWER(1+$B$9,0/12)) -> 1 | I29: =IF($B29=1,E29,F29*G29) -> 1.015092 | J29: =IF($B29=1,0,$B$12+($B$13-$B$12)*(0/23)) -> 10 | K29: =IF($B29=1,0,0.85+0.15*D29) -> 1 | L29: =IF($B29=1,0,MIN($B$13,MAX($B$12,ROUND(J29*K29*F29,0)))) -> 10 | M29: =IF($B29=1,0,1+($B$10*0/12)) -> 1 | N29: =IF($B29=1,0,ROUND($B$8*M29*G29,2)) -> 4221.7 | O29: =ROUND(L29*N29,2) -> 42216.95 | P29: =$B$11 -> 0.02 | Q29: =ROUND(IF(L29>0,O29*P29,0),2) -> 844.34
A30: 2027-04-01 | B30: 2 | C30: phase_2_marketplace_activation | D30: 0.98994723 | E30: =MAX(0.7,1+_xlfn.NORM.INV(RAND(),0,$B$14*0.5)) -> 1 | F30: =MAX(0.85,1+_xlfn.NORM.INV(RAND(),0,$B$14*0.4)) -> 0.985234 | G30: =MAX(0.75,1+_xlfn.NORM.INV(RAND(),0,$B$14*0.35)) -> 0.982243 | H30: =IF($B30=1,1,POWER(1+$B$9,1/12)) -> 1.002466 | I30: =IF($B30=1,E30,F30*G30) -> 0.967739 | J30: =IF($B30=1,0,$B$12+($B$13-$B$12)*(1/23)) -> 26.956522 | K30: =IF($B30=1,0,0.85+0.15*D30) -> 0.99849208 | L30: =IF($B30=1,0,MIN($B$13,MAX($B$12,ROUND(J30*K30*F30,0)))) -> 27 | M30: =IF($B30=1,0,1+($B$10*1/12)) -> 1.0025 | N30: =IF($B30=1,0,ROUND($B$8*M30*G30,2)) -> 4149.08 | O30: =ROUND(L30*N30,2) -> 112025.03 | P30: =$B$11 -> 0.02 | Q30: =ROUND(IF(L30>0,O30*P30,0),2) -> 2240.5
A31: 2027-05-01 | B31: 2 | C31: phase_2_marketplace_activation | D31: 1.1889394 | E31: =MAX(0.7,1+_xlfn.NORM.INV(RAND(),0,$B$14*0.5)) -> 1 | F31: =MAX(0.85,1+_xlfn.NORM.INV(RAND(),0,$B$14*0.4)) -> 1.004927 | G31: =MAX(0.75,1+_xlfn.NORM.INV(RAND(),0,$B$14*0.35)) -> 1.022944 | H31: =IF($B31=1,1,POWER(1+$B$9,2/12)) -> 1.004939 | I31: =IF($B31=1,E31,F31*G31) -> 1.027984 | J31: =IF($B31=1,0,$B$12+($B$13-$B$12)*(2/23)) -> 43.913043 | K31: =IF($B31=1,0,0.85+0.15*D31) -> 1.0283409 | L31: =IF($B31=1,0,MIN($B$13,MAX($B$12,ROUND(J31*K31*F31,0)))) -> 45 | M31: =IF($B31=1,0,1+($B$10*2/12)) -> 1.005 | N31: =IF($B31=1,0,ROUND($B$8*M31*G31,2)) -> 4331.77 | O31: =ROUND(L31*N31,2) -> 194929.79 | P31: =$B$11 -> 0.02 | Q31: =ROUND(IF(L31>0,O31*P31,0),2) -> 3898.6
A32: 2027-06-01 | B32: 2 | C32: phase_2_marketplace_activation | D32: 1.0635797 | E32: =MAX(0.7,1+_xlfn.NORM.INV(RAND(),0,$B$14*0.5)) -> 1 | F32: =MAX(0.85,1+_xlfn.NORM.INV(RAND(),0,$B$14*0.4)) -> 1.000833 | G32: =MAX(0.75,1+_xlfn.NORM.INV(RAND(),0,$B$14*0.35)) -> 0.998139 | H32: =IF($B32=1,1,POWER(1+$B$9,3/12)) -> 1.007417 | I32: =IF($B32=1,E32,F32*G32) -> 0.998971 | J32: =IF($B32=1,0,$B$12+($B$13-$B$12)*(3/23)) -> 60.869565 | K32: =IF($B32=1,0,0.85+0.15*D32) -> 1.009537 | L32: =IF($B32=1,0,MIN($B$13,MAX($B$12,ROUND(J32*K32*F32,0)))) -> 62 | M32: =IF($B32=1,0,1+($B$10*3/12)) -> 1.0075 | N32: =IF($B32=1,0,ROUND($B$8*M32*G32,2)) -> 4237.25 | O32: =ROUND(L32*N32,2) -> 262709.47 | P32: =$B$11 -> 0.02 | Q32: =ROUND(IF(L32>0,O32*P32,0),2) -> 5254.19
A33: 2027-07-01 | B33: 2 | C33: phase_2_marketplace_activation | D33: 1.0466681 | E33: =MAX(0.7,1+_xlfn.NORM.INV(RAND(),0,$B$14*0.5)) -> 1 | F33: =MAX(0.85,1+_xlfn.NORM.INV(RAND(),0,$B$14*0.4)) -> 1.010636 | G33: =MAX(0.75,1+_xlfn.NORM.INV(RAND(),0,$B$14*0.35)) -> 0.974563 | H33: =IF($B33=1,1,POWER(1+$B$9,4/12)) -> 1.009902 | I33: =IF($B33=1,E33,F33*G33) -> 0.984928 | J33: =IF($B33=1,0,$B$12+($B$13-$B$12)*(4/23)) -> 77.826087 | K33: =IF($B33=1,0,0.85+0.15*D33) -> 1.0070002 | L33: =IF($B33=1,0,MIN($B$13,MAX($B$12,ROUND(J33*K33*F33,0)))) -> 79 | M33: =IF($B33=1,0,1+($B$10*4/12)) -> 1.01 | N33: =IF($B33=1,0,ROUND($B$8*M33*G33,2)) -> 4147.43 | O33: =ROUND(L33*N33,2) -> 327646.99 | P33: =$B$11 -> 0.02 | Q33: =ROUND(IF(L33>0,O33*P33,0),2) -> 6552.94
A34: 2027-08-01 | B34: 2 | C34: phase_2_marketplace_activation | D34: 1.0816408 | E34: =MAX(0.7,1+_xlfn.NORM.INV(RAND(),0,$B$14*0.5)) -> 1 | F34: =MAX(0.85,1+_xlfn.NORM.INV(RAND(),0,$B$14*0.4)) -> 0.993754 | G34: =MAX(0.75,1+_xlfn.NORM.INV(RAND(),0,$B$14*0.35)) -> 1.008581 | H34: =IF($B34=1,1,POWER(1+$B$9,5/12)) -> 1.012392 | I34: =IF($B34=1,E34,F34*G34) -> 1.002282 | J34: =IF($B34=1,0,$B$12+($B$13-$B$12)*(5/23)) -> 94.782609 | K34: =IF($B34=1,0,0.85+0.15*D34) -> 1.0122461 | L34: =IF($B34=1,0,MIN($B$13,MAX($B$12,ROUND(J34*K34*F34,0)))) -> 95 | M34: =IF($B34=1,0,1+($B$10*5/12)) -> 1.0125 | N34: =IF($B34=1,0,ROUND($B$8*M34*G34,2)) -> 4302.83 | O34: =ROUND(L34*N34,2) -> 408768.46 | P34: =$B$11 -> 0.02 | Q34: =ROUND(IF(L34>0,O34*P34,0),2) -> 8175.37
A35: 2027-09-01 | B35: 2 | C35: phase_2_marketplace_activation | D35: 1.0397956 | E35: =MAX(0.7,1+_xlfn.NORM.INV(RAND(),0,$B$14*0.5)) -> 1 | F35: =MAX(0.85,1+_xlfn.NORM.INV(RAND(),0,$B$14*0.4)) -> 1.017468 | G35: =MAX(0.75,1+_xlfn.NORM.INV(RAND(),0,$B$14*0.35)) -> 0.995789 | H35: =IF($B35=1,1,POWER(1+$B$9,6/12)) -> 1.014889 | I35: =IF($B35=1,E35,F35*G35) -> 1.013184 | J35: =IF($B35=1,0,$B$12+($B$13-$B$12)*(6/23)) -> 111.73913 | K35: =IF($B35=1,0,0.85+0.15*D35) -> 1.0059693 | L35: =IF($B35=1,0,MIN($B$13,MAX($B$12,ROUND(J35*K35*F35,0)))) -> 114 | M35: =IF($B35=1,0,1+($B$10*6/12)) -> 1.015 | N35: =IF($B35=1,0,ROUND($B$8*M35*G35,2)) -> 4258.74 | O35: =ROUND(L35*N35,2) -> 485496.41 | P35: =$B$11 -> 0.02 | Q35: =ROUND(IF(L35>0,O35*P35,0),2) -> 9709.93
A36: 2027-10-01 | B36: 2 | C36: phase_2_marketplace_activation | D36: 1.0691942 | E36: =MAX(0.7,1+_xlfn.NORM.INV(RAND(),0,$B$14*0.5)) -> 1 | F36: =MAX(0.85,1+_xlfn.NORM.INV(RAND(),0,$B$14*0.4)) -> 1.007532 | G36: =MAX(0.75,1+_xlfn.NORM.INV(RAND(),0,$B$14*0.35)) -> 1.004344 | H36: =IF($B36=1,1,POWER(1+$B$9,7/12)) -> 1.017392 | I36: =IF($B36=1,E36,F36*G36) -> 1.011908 | J36: =IF($B36=1,0,$B$12+($B$13-$B$12)*(7/23)) -> 128.69565 | K36: =IF($B36=1,0,0.85+0.15*D36) -> 1.0103791 | L36: =IF($B36=1,0,MIN($B$13,MAX($B$12,ROUND(J36*K36*F36,0)))) -> 131 | M36: =IF($B36=1,0,1+($B$10*7/12)) -> 1.0175 | N36: =IF($B36=1,0,ROUND($B$8*M36*G36,2)) -> 4305.91 | O36: =ROUND(L36*N36,2) -> 564073.76 | P36: =$B$11 -> 0.02 | Q36: =ROUND(IF(L36>0,O36*P36,0),2) -> 11281.48
A37: 2027-11-01 | B37: 2 | C37: phase_2_marketplace_activation | D37: 1.213324 | E37: =MAX(0.7,1+_xlfn.NORM.INV(RAND(),0,$B$14*0.5)) -> 1 | F37: =MAX(0.85,1+_xlfn.NORM.INV(RAND(),0,$B$14*0.4)) -> 1.015647 | G37: =MAX(0.75,1+_xlfn.NORM.INV(RAND(),0,$B$14*0.35)) -> 0.980519 | H37: =IF($B37=1,1,POWER(1+$B$9,8/12)) -> 1.019901 | I37: =IF($B37=1,E37,F37*G37) -> 0.99586 | J37: =IF($B37=1,0,$B$12+($B$13-$B$12)*(8/23)) -> 145.65217 | K37: =IF($B37=1,0,0.85+0.15*D37) -> 1.0319986 | L37: =IF($B37=1,0,MIN($B$13,MAX($B$12,ROUND(J37*K37*F37,0)))) -> 153 | M37: =IF($B37=1,0,1+($B$10*8/12)) -> 1.02 | N37: =IF($B37=1,0,ROUND($B$8*M37*G37,2)) -> 4214.09 | O37: =ROUND(L37*N37,2) -> 644755.8 | P37: =$B$11 -> 0.02 | Q37: =ROUND(IF(L37>0,O37*P37,0),2) -> 12895.12
A38: 2027-12-01 | B38: 2 | C38: phase_2_marketplace_activation | D38: 2.2762742 | E38: =MAX(0.7,1+_xlfn.NORM.INV(RAND(),0,$B$14*0.5)) -> 1 | F38: =MAX(0.85,1+_xlfn.NORM.INV(RAND(),0,$B$14*0.4)) -> 1.011365 | G38: =MAX(0.75,1+_xlfn.NORM.INV(RAND(),0,$B$14*0.35)) -> 0.973496 | H38: =IF($B38=1,1,POWER(1+$B$9,9/12)) -> 1.022417 | I38: =IF($B38=1,E38,F38*G38) -> 0.98456 | J38: =IF($B38=1,0,$B$12+($B$13-$B$12)*(9/23)) -> 162.6087 | K38: =IF($B38=1,0,0.85+0.15*D38) -> 1.1914411 | L38: =IF($B38=1,0,MIN($B$13,MAX($B$12,ROUND(J38*K38*F38,0)))) -> 196 | M38: =IF($B38=1,0,1+($B$10*9/12)) -> 1.0225 | N38: =IF($B38=1,0,ROUND($B$8*M38*G38,2)) -> 4194.16 | O38: =ROUND(L38*N38,2) -> 822055.85 | P38: =$B$11 -> 0.02 | Q38: =ROUND(IF(L38>0,O38*P38,0),2) -> 16441.12
A39: 2028-01-01 | B39: 2 | C39: phase_2_marketplace_activation | D39: 0.94587711 | E39: =MAX(0.7,1+_xlfn.NORM.INV(RAND(),0,$B$14*0.5)) -> 1 | F39: =MAX(0.85,1+_xlfn.NORM.INV(RAND(),0,$B$14*0.4)) -> 0.947601 | G39: =MAX(0.75,1+_xlfn.NORM.INV(RAND(),0,$B$14*0.35)) -> 0.989379 | H39: =IF($B39=1,1,POWER(1+$B$9,10/12)) -> 1.024938 | I39: =IF($B39=1,E39,F39*G39) -> 0.937537 | J39: =IF($B39=1,0,$B$12+($B$13-$B$12)*(10/23)) -> 179.56522 | K39: =IF($B39=1,0,0.85+0.15*D39) -> 0.99188157 | L39: =IF($B39=1,0,MIN($B$13,MAX($B$12,ROUND(J39*K39*F39,0)))) -> 169 | M39: =IF($B39=1,0,1+($B$10*10/12)) -> 1.025 | N39: =IF($B39=1,0,ROUND($B$8*M39*G39,2)) -> 4273.02 | O39: =ROUND(L39*N39,2) -> 722139.75 | P39: =$B$11 -> 0.02 | Q39: =ROUND(IF(L39>0,O39*P39,0),2) -> 14442.79
A40: 2028-02-01 | B40: 2 | C40: phase_2_marketplace_activation | D40: 1.167967 | E40: =MAX(0.7,1+_xlfn.NORM.INV(RAND(),0,$B$14*0.5)) -> 1 | F40: =MAX(0.85,1+_xlfn.NORM.INV(RAND(),0,$B$14*0.4)) -> 0.981684 | G40: =MAX(0.75,1+_xlfn.NORM.INV(RAND(),0,$B$14*0.35)) -> 1.01533 | H40: =IF($B40=1,1,POWER(1+$B$9,11/12)) -> 1.027466 | I40: =IF($B40=1,E40,F40*G40) -> 0.996733 | J40: =IF($B40=1,0,$B$12+($B$13-$B$12)*(11/23)) -> 196.52174 | K40: =IF($B40=1,0,0.85+0.15*D40) -> 1.0251951 | L40: =IF($B40=1,0,MIN($B$13,MAX($B$12,ROUND(J40*K40*F40,0)))) -> 198 | M40: =IF($B40=1,0,1+($B$10*11/12)) -> 1.0275 | N40: =IF($B40=1,0,ROUND($B$8*M40*G40,2)) -> 4395.79 | O40: =ROUND(L40*N40,2) -> 870366.45 | P40: =$B$11 -> 0.02 | Q40: =ROUND(IF(L40>0,O40*P40,0),2) -> 17407.33
A41: 2028-03-01 | B41: 3 | C41: phase_3_projection | D41: 1 | E41: =MAX(0.7,1+_xlfn.NORM.INV(RAND(),0,$B$14*0.5)) -> 1 | F41: =MAX(0.85,1+_xlfn.NORM.INV(RAND(),0,$B$14*0.4)) -> 1.013285 | G41: =MAX(0.75,1+_xlfn.NORM.INV(RAND(),0,$B$14*0.35)) -> 0.978666 | H41: =IF($B41=1,1,POWER(1+$B$9,12/12)) -> 1.03 | I41: =IF($B41=1,E41,F41*G41) -> 0.991668 | J41: =IF($B41=1,0,$B$12+($B$13-$B$12)*(12/23)) -> 213.47826 | K41: =IF($B41=1,0,0.85+0.15*D41) -> 1 | L41: =IF($B41=1,0,MIN($B$13,MAX($B$12,ROUND(J41*K41*F41,0)))) -> 216 | M41: =IF($B41=1,0,1+($B$10*12/12)) -> 1.03 | N41: =IF($B41=1,0,ROUND($B$8*M41*G41,2)) -> 4247.37 | O41: =ROUND(L41*N41,2) -> 917430.92 | P41: =$B$11 -> 0.02 | Q41: =ROUND(IF(L41>0,O41*P41,0),2) -> 18348.62
A42: 2028-04-01 | B42: 3 | C42: phase_3_projection | D42: 0.98994723 | E42: =MAX(0.7,1+_xlfn.NORM.INV(RAND(),0,$B$14*0.5)) -> 1 | F42: =MAX(0.85,1+_xlfn.NORM.INV(RAND(),0,$B$14*0.4)) -> 1.016947 | G42: =MAX(0.75,1+_xlfn.NORM.INV(RAND(),0,$B$14*0.35)) -> 0.982461 | H42: =IF($B42=1,1,POWER(1+$B$9,13/12)) -> 1.03254 | I42: =IF($B42=1,E42,F42*G42) -> 0.999111 | J42: =IF($B42=1,0,$B$12+($B$13-$B$12)*(13/23)) -> 230.43478 | K42: =IF($B42=1,0,0.85+0.15*D42) -> 0.99849208 | L42: =IF($B42=1,0,MIN($B$13,MAX($B$12,ROUND(J42*K42*F42,0)))) -> 234 | M42: =IF($B42=1,0,1+($B$10*13/12)) -> 1.0325 | N42: =IF($B42=1,0,ROUND($B$8*M42*G42,2)) -> 4274.19 | O42: =ROUND(L42*N42,2) -> 1000159.5 | P42: =$B$11 -> 0.02 | Q42: =ROUND(IF(L42>0,O42*P42,0),2) -> 20003.19
A43: 2028-05-01 | B43: 3 | C43: phase_3_projection | D43: 1.1889394 | E43: =MAX(0.7,1+_xlfn.NORM.INV(RAND(),0,$B$14*0.5)) -> 1 | F43: =MAX(0.85,1+_xlfn.NORM.INV(RAND(),0,$B$14*0.4)) -> 0.998275 | G43: =MAX(0.75,1+_xlfn.NORM.INV(RAND(),0,$B$14*0.35)) -> 0.994857 | H43: =IF($B43=1,1,POWER(1+$B$9,14/12)) -> 1.035087 | I43: =IF($B43=1,E43,F43*G43) -> 0.993141 | J43: =IF($B43=1,0,$B$12+($B$13-$B$12)*(14/23)) -> 247.3913 | K43: =IF($B43=1,0,0.85+0.15*D43) -> 1.0283409 | L43: =IF($B43=1,0,MIN($B$13,MAX($B$12,ROUND(J43*K43*F43,0)))) -> 254 | M43: =IF($B43=1,0,1+($B$10*14/12)) -> 1.035 | N43: =IF($B43=1,0,ROUND($B$8*M43*G43,2)) -> 4338.59 | O43: =ROUND(L43*N43,2) -> 1102002.1 | P43: =$B$11 -> 0.02 | Q43: =ROUND(IF(L43>0,O43*P43,0),2) -> 22040.04
A44: 2028-06-01 | B44: 3 | C44: phase_3_projection | D44: 1.0635797 | E44: =MAX(0.7,1+_xlfn.NORM.INV(RAND(),0,$B$14*0.5)) -> 1 | F44: =MAX(0.85,1+_xlfn.NORM.INV(RAND(),0,$B$14*0.4)) -> 1.002288 | G44: =MAX(0.75,1+_xlfn.NORM.INV(RAND(),0,$B$14*0.35)) -> 1.014326 | H44: =IF($B44=1,1,POWER(1+$B$9,15/12)) -> 1.03764 | I44: =IF($B44=1,E44,F44*G44) -> 1.016647 | J44: =IF($B44=1,0,$B$12+($B$13-$B$12)*(15/23)) -> 264.34783 | K44: =IF($B44=1,0,0.85+0.15*D44) -> 1.009537 | L44: =IF($B44=1,0,MIN($B$13,MAX($B$12,ROUND(J44*K44*F44,0)))) -> 267 | M44: =IF($B44=1,0,1+($B$10*15/12)) -> 1.0375 | N44: =IF($B44=1,0,ROUND($B$8*M44*G44,2)) -> 4434.18 | O44: =ROUND(L44*N44,2) -> 1183926.6 | P44: =$B$11 -> 0.02 | Q44: =ROUND(IF(L44>0,O44*P44,0),2) -> 23678.53
A45: 2028-07-01 | B45: 3 | C45: phase_3_projection | D45: 1.0466681 | E45: =MAX(0.7,1+_xlfn.NORM.INV(RAND(),0,$B$14*0.5)) -> 1 | F45: =MAX(0.85,1+_xlfn.NORM.INV(RAND(),0,$B$14*0.4)) -> 1.012768 | G45: =MAX(0.75,1+_xlfn.NORM.INV(RAND(),0,$B$14*0.35)) -> 1.006123 | H45: =IF($B45=1,1,POWER(1+$B$9,16/12)) -> 1.040199 | I45: =IF($B45=1,E45,F45*G45) -> 1.018969 | J45: =IF($B45=1,0,$B$12+($B$13-$B$12)*(16/23)) -> 281.30435 | K45: =IF($B45=1,0,0.85+0.15*D45) -> 1.0070002 | L45: =IF($B45=1,0,MIN($B$13,MAX($B$12,ROUND(J45*K45*F45,0)))) -> 287 | M45: =IF($B45=1,0,1+($B$10*16/12)) -> 1.04 | N45: =IF($B45=1,0,ROUND($B$8*M45*G45,2)) -> 4408.92 | O45: =ROUND(L45*N45,2) -> 1265360.1 | P45: =$B$11 -> 0.02 | Q45: =ROUND(IF(L45>0,O45*P45,0),2) -> 25307.2
A46: 2028-08-01 | B46: 3 | C46: phase_3_projection | D46: 1.0816408 | E46: =MAX(0.7,1+_xlfn.NORM.INV(RAND(),0,$B$14*0.5)) -> 1 | F46: =MAX(0.85,1+_xlfn.NORM.INV(RAND(),0,$B$14*0.4)) -> 1.012999 | G46: =MAX(0.75,1+_xlfn.NORM.INV(RAND(),0,$B$14*0.35)) -> 1.008374 | H46: =IF($B46=1,1,POWER(1+$B$9,17/12)) -> 1.042764 | I46: =IF($B46=1,E46,F46*G46) -> 1.021481 | J46: =IF($B46=1,0,$B$12+($B$13-$B$12)*(17/23)) -> 298.26087 | K46: =IF($B46=1,0,0.85+0.15*D46) -> 1.0122461 | L46: =IF($B46=1,0,MIN($B$13,MAX($B$12,ROUND(J46*K46*F46,0)))) -> 306 | M46: =IF($B46=1,0,1+($B$10*17/12)) -> 1.0425 | N46: =IF($B46=1,0,ROUND($B$8*M46*G46,2)) -> 4429.4 | O46: =ROUND(L46*N46,2) -> 1355397.8 | P46: =$B$11 -> 0.02 | Q46: =ROUND(IF(L46>0,O46*P46,0),2) -> 27107.96
A47: 2028-09-01 | B47: 3 | C47: phase_3_projection | D47: 1.0397956 | E47: =MAX(0.7,1+_xlfn.NORM.INV(RAND(),0,$B$14*0.5)) -> 1 | F47: =MAX(0.85,1+_xlfn.NORM.INV(RAND(),0,$B$14*0.4)) -> 0.98746 | G47: =MAX(0.75,1+_xlfn.NORM.INV(RAND(),0,$B$14*0.35)) -> 0.987446 | H47: =IF($B47=1,1,POWER(1+$B$9,18/12)) -> 1.045336 | I47: =IF($B47=1,E47,F47*G47) -> 0.975064 | J47: =IF($B47=1,0,$B$12+($B$13-$B$12)*(18/23)) -> 315.21739 | K47: =IF($B47=1,0,0.85+0.15*D47) -> 1.0059693 | L47: =IF($B47=1,0,MIN($B$13,MAX($B$12,ROUND(J47*K47*F47,0)))) -> 313 | M47: =IF($B47=1,0,1+($B$10*18/12)) -> 1.045 | N47: =IF($B47=1,0,ROUND($B$8*M47*G47,2)) -> 4347.88 | O47: =ROUND(L47*N47,2) -> 1360886.2 | P47: =$B$11 -> 0.02 | Q47: =ROUND(IF(L47>0,O47*P47,0),2) -> 27217.72
A48: 2028-10-01 | B48: 3 | C48: phase_3_projection | D48: 1.0691942 | E48: =MAX(0.7,1+_xlfn.NORM.INV(RAND(),0,$B$14*0.5)) -> 1 | F48: =MAX(0.85,1+_xlfn.NORM.INV(RAND(),0,$B$14*0.4)) -> 0.990601 | G48: =MAX(0.75,1+_xlfn.NORM.INV(RAND(),0,$B$14*0.35)) -> 1.008738 | H48: =IF($B48=1,1,POWER(1+$B$9,19/12)) -> 1.047914 | I48: =IF($B48=1,E48,F48*G48) -> 0.999257 | J48: =IF($B48=1,0,$B$12+($B$13-$B$12)*(19/23)) -> 332.17391 | K48: =IF($B48=1,0,0.85+0.15*D48) -> 1.0103791 | L48: =IF($B48=1,0,MIN($B$13,MAX($B$12,ROUND(J48*K48*F48,0)))) -> 332 | M48: =IF($B48=1,0,1+($B$10*19/12)) -> 1.0475 | N48: =IF($B48=1,0,ROUND($B$8*M48*G48,2)) -> 4452.26 | O48: =ROUND(L48*N48,2) -> 1478149.6 | P48: =$B$11 -> 0.02 | Q48: =ROUND(IF(L48>0,O48*P48,0),2) -> 29562.99
A49: 2028-11-01 | B49: 3 | C49: phase_3_projection | D49: 1.213324 | E49: =MAX(0.7,1+_xlfn.NORM.INV(RAND(),0,$B$14*0.5)) -> 1 | F49: =MAX(0.85,1+_xlfn.NORM.INV(RAND(),0,$B$14*0.4)) -> 0.994998 | G49: =MAX(0.75,1+_xlfn.NORM.INV(RAND(),0,$B$14*0.35)) -> 1.040876 | H49: =IF($B49=1,1,POWER(1+$B$9,20/12)) -> 1.050498 | I49: =IF($B49=1,E49,F49*G49) -> 1.035669 | J49: =IF($B49=1,0,$B$12+($B$13-$B$12)*(20/23)) -> 349.13043 | K49: =IF($B49=1,0,0.85+0.15*D49) -> 1.0319986 | L49: =IF($B49=1,0,MIN($B$13,MAX($B$12,ROUND(J49*K49*F49,0)))) -> 358 | M49: =IF($B49=1,0,1+($B$10*20/12)) -> 1.05 | N49: =IF($B49=1,0,ROUND($B$8*M49*G49,2)) -> 4605.07 | O49: =ROUND(L49*N49,2) -> 1648614.1 | P49: =$B$11 -> 0.02 | Q49: =ROUND(IF(L49>0,O49*P49,0),2) -> 32972.28
A50: 2028-12-01 | B50: 3 | C50: phase_3_projection | D50: 2.2762742 | E50: =MAX(0.7,1+_xlfn.NORM.INV(RAND(),0,$B$14*0.5)) -> 1 | F50: =MAX(0.85,1+_xlfn.NORM.INV(RAND(),0,$B$14*0.4)) -> 0.983614 | G50: =MAX(0.75,1+_xlfn.NORM.INV(RAND(),0,$B$14*0.35)) -> 0.98077 | H50: =IF($B50=1,1,POWER(1+$B$9,21/12)) -> 1.053089 | I50: =IF($B50=1,E50,F50*G50) -> 0.964699 | J50: =IF($B50=1,0,$B$12+($B$13-$B$12)*(21/23)) -> 366.08696 | K50: =IF($B50=1,0,0.85+0.15*D50) -> 1.1914411 | L50: =IF($B50=1,0,MIN($B$13,MAX($B$12,ROUND(J50*K50*F50,0)))) -> 400 | M50: =IF($B50=1,0,1+($B$10*21/12)) -> 1.0525 | N50: =IF($B50=1,0,ROUND($B$8*M50*G50,2)) -> 4349.48 | O50: =ROUND(L50*N50,2) -> 1739790.5 | P50: =$B$11 -> 0.02 | Q50: =ROUND(IF(L50>0,O50*P50,0),2) -> 34795.81
A51: 2029-01-01 | B51: 3 | C51: phase_3_projection | D51: 0.94587711 | E51: =MAX(0.7,1+_xlfn.NORM.INV(RAND(),0,$B$14*0.5)) -> 1 | F51: =MAX(0.85,1+_xlfn.NORM.INV(RAND(),0,$B$14*0.4)) -> 1.015369 | G51: =MAX(0.75,1+_xlfn.NORM.INV(RAND(),0,$B$14*0.35)) -> 1.024882 | H51: =IF($B51=1,1,POWER(1+$B$9,22/12)) -> 1.055686 | I51: =IF($B51=1,E51,F51*G51) -> 1.040634 | J51: =IF($B51=1,0,$B$12+($B$13-$B$12)*(22/23)) -> 383.04348 | K51: =IF($B51=1,0,0.85+0.15*D51) -> 0.99188157 | L51: =IF($B51=1,0,MIN($B$13,MAX($B$12,ROUND(J51*K51*F51,0)))) -> 386 | M51: =IF($B51=1,0,1+($B$10*22/12)) -> 1.055 | N51: =IF($B51=1,0,ROUND($B$8*M51*G51,2)) -> 4555.9 | O51: =ROUND(L51*N51,2) -> 1758577.9 | P51: =$B$11 -> 0.02 | Q51: =ROUND(IF(L51>0,O51*P51,0),2) -> 35171.56
A52: 2029-02-01 | B52: 3 | C52: phase_3_projection | D52: 1.167967 | E52: =MAX(0.7,1+_xlfn.NORM.INV(RAND(),0,$B$14*0.5)) -> 1 | F52: =MAX(0.85,1+_xlfn.NORM.INV(RAND(),0,$B$14*0.4)) -> 1.010114 | G52: =MAX(0.75,1+_xlfn.NORM.INV(RAND(),0,$B$14*0.35)) -> 1.014627 | H52: =IF($B52=1,1,POWER(1+$B$9,23/12)) -> 1.05829 | I52: =IF($B52=1,E52,F52*G52) -> 1.024889 | J52: =IF($B52=1,0,$B$12+($B$13-$B$12)*(23/23)) -> 400 | K52: =IF($B52=1,0,0.85+0.15*D52) -> 1.0251951 | L52: =IF($B52=1,0,MIN($B$13,MAX($B$12,ROUND(J52*K52*F52,0)))) -> 400 | M52: =IF($B52=1,0,1+($B$10*23/12)) -> 1.0575 | N52: =IF($B52=1,0,ROUND($B$8*M52*G52,2)) -> 4521 | O52: =ROUND(L52*N52,2) -> 1808400.1 | P52: =$B$11 -> 0.02 | Q52: =ROUND(IF(L52>0,O52*P52,0),2) -> 36168

Sheet MAU
A1: [MAU Assumptions] | C1: Inputs used by the MAU rollup and cohort acquisition/retention model below.
A2: name | B2: value | C2: details
A3: projection_months | B3: 36 | C3: Number of projected monthly rows in the workbook model.
A4: projection_start_month | B4: 2026-03 | C4: First month of the synthetic projection in YYYY-MM format.
A5: new_users_start | B5: 700 | C5: New users acquired in the first projected cohort month.
A6: new_users_monthly_growth_year1 | B6: 0.1 | C6: Monthly new-user growth rate applied in Year 1.
A7: new_users_monthly_growth_year2 | B7: 0.05 | C7: Monthly new-user growth rate applied in Year 2.
A8: new_users_monthly_growth_year3 | B8: 0.03 | C8: Monthly new-user growth rate applied in Year 3.
A9: new_user_holiday_spike_multiplier | B9: 1.3 | C9: Extra acquisition multiplier applied in November and December.
A10: base_new_users_rule | B10: Month 0 = start; later months = prior month * (1 + current growth rate) | C10: Human-readable formula for the base_new_users column before seasonality, holiday spike, and noise are applied.
A11: user_retention_month_1 | B11: 0.25 | C11: Share of a cohort still active one month after signup.
A12: user_retention_month_2 | B12: 0.12 | C12: Share of a cohort still active two months after signup.
A13: user_retention_month_3 | B13: 0.05 | C13: Share of a cohort still active three months after signup.
A14: user_retention_decay | B14: 0.97 | C14: Monthly decay applied to cohort retention after Month 3.
A15: jitter_std | B15: 0.05 | C15: Standard deviation used by cohort acquisition noise.
A16: dependency | B16: MAU cohort matrix on this sheet | C16: MAU is derived by summing active cohort contributions from the cohort matrix on this sheet.
A18: month | B18: year_index | C18: phase | D18: new_users | E18: returning_users | F18: mau | H18: acquisition_growth_rate | I18: base_new_users | J18: seasonality_factor | K18: noise_acquisition | M18: user_retention_age | N18: user_retained_share | O18: 2026-03-01 | P18: 2026-04-01 | Q18: 2026-05-01 | R18: 2026-06-01 | S18: 2026-07-01 | T18: 2026-08-01 | U18: 2026-09-01 | V18: 2026-10-01 | W18: 2026-11-01 | X18: 2026-12-01 | Y18: 2027-01-01 | Z18: 2027-02-01 | AA18: 2027-03-01 | AB18: 2027-04-01 | AC18: 2027-05-01 | AD18: 2027-06-01 | AE18: 2027-07-01 | AF18: 2027-08-01 | AG18: 2027-09-01 | AH18: 2027-10-01 | AI18: 2027-11-01 | AJ18: 2027-12-01 | AK18: 2028-01-01 | AL18: 2028-02-01 | AM18: 2028-03-01 | AN18: 2028-04-01 | AO18: 2028-05-01 | AP18: 2028-06-01 | AQ18: 2028-07-01 | AR18: 2028-08-01 | AS18: 2028-09-01 | AT18: 2028-10-01 | AU18: 2028-11-01 | AV18: 2028-12-01 | AW18: 2029-01-01 | AX18: 2029-02-01
A19: 2026-03-01 | B19: 1 | C19: phase_1_user_growth | D19: =ROUND(MAX(100,I19*J19*K19),0) -> 613 | E19: =MAX(0,F19-D19) -> 0 | F19: =ROUND(SUM($O$19:$O$54),0) -> 613 | H19: =IF($B19=1,$B$6,IF($B19=2,$B$7,$B$8)) -> 0.1 | I19: =$B$5 -> 700 | J19: 0.852079 | K19: =MAX(0.85,1+_xlfn.NORM.INV(RAND(),0,$B$15*0.35)) -> 1.028427 | M19: 0 | N19: =IF($M19=0,1,IF($M19=1,$B$11,IF($M19=2,$B$12,IF($M19=3,$B$13,$B$13*POWER($B$14,$M19-3)))) -> 1 | O19: =ROUND(D19*INDEX($N$19:$N$54,1),0) -> 613 | P19: =ROUND(D19*INDEX($N$19:$N$54,2),0) -> 153 | Q19: =ROUND(D19*INDEX($N$19:$N$54,3),0) -> 74 | R19: =ROUND(D19*INDEX($N$19:$N$54,4),0) -> 31 | S19: =ROUND(D19*INDEX($N$19:$N$54,5),0) -> 30 | T19: =ROUND(D19*INDEX($N$19:$N$54,6),0) -> 29 | U19: =ROUND(D19*INDEX($N$19:$N$54,7),0) -> 28 | V19: =ROUND(D19*INDEX($N$19:$N$54,8),0) -> 27 | W19: =ROUND(D19*INDEX($N$19:$N$54,9),0) -> 26 | X19: =ROUND(D19*INDEX($N$19:$N$54,10),0) -> 26 | Y19: =ROUND(D19*INDEX($N$19:$N$54,11),0) -> 25 | Z19: =ROUND(D19*INDEX($N$19:$N$54,12),0) -> 24 | AA19: =ROUND(D19*INDEX($N$19:$N$54,13),0) -> 23 | AB19: =ROUND(D19*INDEX($N$19:$N$54,14),0) -> 23 | AC19: =ROUND(D19*INDEX($N$19:$N$54,15),0) -> 22 | AD19: =ROUND(D19*INDEX($N$19:$N$54,16),0) -> 21 | AE19: =ROUND(D19*INDEX($N$19:$N$54,17),0) -> 21 | AF19: =ROUND(D19*INDEX($N$19:$N$54,18),0) -> 20 | AG19: =ROUND(D19*INDEX($N$19:$N$54,19),0) -> 19 | AH19: =ROUND(D19*INDEX($N$19:$N$54,20),0) -> 19 | AI19: =ROUND(D19*INDEX($N$19:$N$54,21),0) -> 18 | AJ19: =ROUND(D19*INDEX($N$19:$N$54,22),0) -> 18 | AK19: =ROUND(D19*INDEX($N$19:$N$54,23),0) -> 17 | AL19: =ROUND(D19*INDEX($N$19:$N$54,24),0) -> 17 | AM19: =ROUND(D19*INDEX($N$19:$N$54,25),0) -> 16 | AN19: =ROUND(D19*INDEX($N$19:$N$54,26),0) -> 16 | AO19: =ROUND(D19*INDEX($N$19:$N$54,27),0) -> 15 | AP19: =ROUND(D19*INDEX($N$19:$N$54,28),0) -> 15 | AQ19: =ROUND(D19*INDEX($N$19:$N$54,29),0) -> 14 | AR19: =ROUND(D19*INDEX($N$19:$N$54,30),0) -> 14 | AS19: =ROUND(D19*INDEX($N$19:$N$54,31),0) -> 13 | AT19: =ROUND(D19*INDEX($N$19:$N$54,32),0) -> 13 | AU19: =ROUND(D19*INDEX($N$19:$N$54,33),0) -> 13 | AV19: =ROUND(D19*INDEX($N$19:$N$54,34),0) -> 12 | AW19: =ROUND(D19*INDEX($N$19:$N$54,35),0) -> 12 | AX19: =ROUND(D19*INDEX($N$19:$N$54,36),0) -> 12
A20: 2026-04-01 | B20: 1 | C20: phase_1_user_growth | D20: =ROUND(MAX(100,I20*J20*K20),0) -> 637 | E20: =MAX(0,F20-D20) -> 153 | F20: =ROUND(SUM($P$19:$P$54),0) -> 790 | H20: =IF($B20=1,$B$6,IF($B20=2,$B$7,$B$8)) -> 0.1 | I20: =I19*(1+H20) -> 770 | J20: 0.843513 | K20: =MAX(0.85,1+_xlfn.NORM.INV(RAND(),0,$B$15*0.35)) -> 0.981037 | M20: 1 | N20: =IF($M20=0,1,IF($M20=1,$B$11,IF($M20=2,$B$12,IF($M20=3,$B$13,$B$13*POWER($B$14,$M20-3)))) -> 0.25 | P20: =ROUND(D20*INDEX($N$19:$N$54,1),0) -> 637 | Q20: =ROUND(D20*INDEX($N$19:$N$54,2),0) -> 159 | R20: =ROUND(D20*INDEX($N$19:$N$54,3),0) -> 76 | S20: =ROUND(D20*INDEX($N$19:$N$54,4),0) -> 32 | T20: =ROUND(D20*INDEX($N$19:$N$54,5),0) -> 31 | U20: =ROUND(D20*INDEX($N$19:$N$54,6),0) -> 30 | V20: =ROUND(D20*INDEX($N$19:$N$54,7),0) -> 29 | W20: =ROUND(D20*INDEX($N$19:$N$54,8),0) -> 28 | X20: =ROUND(D20*INDEX($N$19:$N$54,9),0) -> 27 | Y20: =ROUND(D20*INDEX($N$19:$N$54,10),0) -> 27 | Z20: =ROUND(D20*INDEX($N$19:$N$54,11),0) -> 26 | AA20: =ROUND(D20*INDEX($N$19:$N$54,12),0) -> 25 | AB20: =ROUND(D20*INDEX($N$19:$N$54,13),0) -> 24 | AC20: =ROUND(D20*INDEX($N$19:$N$54,14),0) -> 23 | AD20: =ROUND(D20*INDEX($N$19:$N$54,15),0) -> 23 | AE20: =ROUND(D20*INDEX($N$19:$N$54,16),0) -> 22 | AF20: =ROUND(D20*INDEX($N$19:$N$54,17),0) -> 21 | AG20: =ROUND(D20*INDEX($N$19:$N$54,18),0) -> 21 | AH20: =ROUND(D20*INDEX($N$19:$N$54,19),0) -> 20 | AI20: =ROUND(D20*INDEX($N$19:$N$54,20),0) -> 20 | AJ20: =ROUND(D20*INDEX($N$19:$N$54,21),0) -> 19 | AK20: =ROUND(D20*INDEX($N$19:$N$54,22),0) -> 18 | AL20: =ROUND(D20*INDEX($N$19:$N$54,23),0) -> 18 | AM20: =ROUND(D20*INDEX($N$19:$N$54,24),0) -> 17 | AN20: =ROUND(D20*INDEX($N$19:$N$54,25),0) -> 17 | AO20: =ROUND(D20*INDEX($N$19:$N$54,26),0) -> 16 | AP20: =ROUND(D20*INDEX($N$19:$N$54,27),0) -> 16 | AQ20: =ROUND(D20*INDEX($N$19:$N$54,28),0) -> 15 | AR20: =ROUND(D20*INDEX($N$19:$N$54,29),0) -> 15 | AS20: =ROUND(D20*INDEX($N$19:$N$54,30),0) -> 14 | AT20: =ROUND(D20*INDEX($N$19:$N$54,31),0) -> 14 | AU20: =ROUND(D20*INDEX($N$19:$N$54,32),0) -> 14 | AV20: =ROUND(D20*INDEX($N$19:$N$54,33),0) -> 13 | AW20: =ROUND(D20*INDEX($N$19:$N$54,34),0) -> 13 | AX20: =ROUND(D20*INDEX($N$19:$N$54,35),0) -> 12
A21: 2026-05-01 | B21: 1 | C21: phase_1_user_growth | D21: =ROUND(MAX(100,I21*J21*K21),0) -> 868 | E21: =MAX(0,F21-D21) -> 233 | F21: =ROUND(SUM($Q$19:$Q$54),0) -> 1101 | H21: =IF($B21=1,$B$6,IF($B21=2,$B$7,$B$8)) -> 0.1 | I21: =I20*(1+H21) -> 847 | J21: 1.01307 | K21: =MAX(0.85,1+_xlfn.NORM.INV(RAND(),0,$B$15*0.35)) -> 1.012013 | M21: 2 | N21: =IF($M21=0,1,IF($M21=1,$B$11,IF($M21=2,$B$12,IF($M21=3,$B$13,$B$13*POWER($B$14,$M21-3)))) -> 0.12 | Q21: =ROUND(D21*INDEX($N$19:$N$54,1),0) -> 868 | R21: =ROUND(D21*INDEX($N$19:$N$54,2),0) -> 217 | S21: =ROUND(D21*INDEX($N$19:$N$54,3),0) -> 104 | T21: =ROUND(D21*INDEX($N$19:$N$54,4),0) -> 43 | U21: =ROUND(D21*INDEX($N$19:$N$54,5),0) -> 42 | V21: =ROUND(D21*INDEX($N$19:$N$54,6),0) -> 41 | W21: =ROUND(D21*INDEX($N$19:$N$54,7),0) -> 40 | X21: =ROUND(D21*INDEX($N$19:$N$54,8),0) -> 38 | Y21: =ROUND(D21*INDEX($N$19:$N$54,9),0) -> 37 | Z21: =ROUND(D21*INDEX($N$19:$N$54,10),0) -> 36 | AA21: =ROUND(D21*INDEX($N$19:$N$54,11),0) -> 35 | AB21: =ROUND(D21*INDEX($N$19:$N$54,12),0) -> 34 | AC21: =ROUND(D21*INDEX($N$19:$N$54,13),0) -> 33 | AD21: =ROUND(D21*INDEX($N$19:$N$54,14),0) -> 32 | AE21: =ROUND(D21*INDEX($N$19:$N$54,15),0) -> 31 | AF21: =ROUND(D21*INDEX($N$19:$N$54,16),0) -> 30 | AG21: =ROUND(D21*INDEX($N$19:$N$54,17),0) -> 29 | AH21: =ROUND(D21*INDEX($N$19:$N$54,18),0) -> 28 | AI21: =ROUND(D21*INDEX($N$19:$N$54,19),0) -> 27 | AJ21: =ROUND(D21*INDEX($N$19:$N$54,20),0) -> 27 | AK21: =ROUND(D21*INDEX($N$19:$N$54,21),0) -> 26 | AL21: =ROUND(D21*INDEX($N$19:$N$54,22),0) -> 25 | AM21: =ROUND(D21*INDEX($N$19:$N$54,23),0) -> 24 | AN21: =ROUND(D21*INDEX($N$19:$N$54,24),0) -> 24 | AO21: =ROUND(D21*INDEX($N$19:$N$54,25),0) -> 23 | AP21: =ROUND(D21*INDEX($N$19:$N$54,26),0) -> 22 | AQ21: =ROUND(D21*INDEX($N$19:$N$54,27),0) -> 22 | AR21: =ROUND(D21*INDEX($N$19:$N$54,28),0) -> 21 | AS21: =ROUND(D21*INDEX($N$19:$N$54,29),0) -> 20 | AT21: =ROUND(D21*INDEX($N$19:$N$54,30),0) -> 20 | AU21: =ROUND(D21*INDEX($N$19:$N$54,31),0) -> 19 | AV21: =ROUND(D21*INDEX($N$19:$N$54,32),0) -> 18 | AW21: =ROUND(D21*INDEX($N$19:$N$54,33),0) -> 18 | AX21: =ROUND(D21*INDEX($N$19:$N$54,34),0) -> 17
A22: 2026-06-01 | B22: 1 | C22: phase_1_user_growth | D22: =ROUND(MAX(100,I22*J22*K22),0) -> 847 | E22: =MAX(0,F22-D22) -> 324 | F22: =ROUND(SUM($R$19:$R$54),0) -> 1171 | H22: =IF($B22=1,$B$6,IF($B22=2,$B$7,$B$8)) -> 0.1 | I22: =I21*(1+H22) -> 931.7 | J22: 0.906254 | K22: =MAX(0.85,1+_xlfn.NORM.INV(RAND(),0,$B$15*0.35)) -> 1.003557 | M22: 3 | N22: =IF($M22=0,1,IF($M22=1,$B$11,IF($M22=2,$B$12,IF($M22=3,$B$13,$B$13*POWER($B$14,$M22-3)))) -> 0.05 | R22: =ROUND(D22*INDEX($N$19:$N$54,1),0) -> 847 | S22: =ROUND(D22*INDEX($N$19:$N$54,2),0) -> 212 | T22: =ROUND(D22*INDEX($N$19:$N$54,3),0) -> 102 | U22: =ROUND(D22*INDEX($N$19:$N$54,4),0) -> 42 | V22: =ROUND(D22*INDEX($N$19:$N$54,5),0) -> 41 | W22: =ROUND(D22*INDEX($N$19:$N$54,6),0) -> 40 | X22: =ROUND(D22*INDEX($N$19:$N$54,7),0) -> 39 | Y22: =ROUND(D22*INDEX($N$19:$N$54,8),0) -> 37 | Z22: =ROUND(D22*INDEX($N$19:$N$54,9),0) -> 36 | AA22: =ROUND(D22*INDEX($N$19:$N$54,10),0) -> 35 | AB22: =ROUND(D22*INDEX($N$19:$N$54,11),0) -> 34 | AC22: =ROUND(D22*INDEX($N$19:$N$54,12),0) -> 33 | AD22: =ROUND(D22*INDEX($N$19:$N$54,13),0) -> 32 | AE22: =ROUND(D22*INDEX($N$19:$N$54,14),0) -> 31 | AF22: =ROUND(D22*INDEX($N$19:$N$54,15),0) -> 30 | AG22: =ROUND(D22*INDEX($N$19:$N$54,16),0) -> 29 | AH22: =ROUND(D22*INDEX($N$19:$N$54,17),0) -> 29 | AI22: =ROUND(D22*INDEX($N$19:$N$54,18),0) -> 28 | AJ22: =ROUND(D22*INDEX($N$19:$N$54,19),0) -> 27 | AK22: =ROUND(D22*INDEX($N$19:$N$54,20),0) -> 26 | AL22: =ROUND(D22*INDEX($N$19:$N$54,21),0) -> 25 | AM22: =ROUND(D22*INDEX($N$19:$N$54,22),0) -> 24 | AN22: =ROUND(D22*INDEX($N$19:$N$54,23),0) -> 24 | AO22: =ROUND(D22*INDEX($N$19:$N$54,24),0) -> 23 | AP22: =ROUND(D22*INDEX($N$19:$N$54,25),0) -> 22 | AQ22: =ROUND(D22*INDEX($N$19:$N$54,26),0) -> 22 | AR22: =ROUND(D22*INDEX($N$19:$N$54,27),0) -> 21 | AS22: =ROUND(D22*INDEX($N$19:$N$54,28),0) -> 20 | AT22: =ROUND(D22*INDEX($N$19:$N$54,29),0) -> 20 | AU22: =ROUND(D22*INDEX($N$19:$N$54,30),0) -> 19 | AV22: =ROUND(D22*INDEX($N$19:$N$54,31),0) -> 19 | AW22: =ROUND(D22*INDEX($N$19:$N$54,32),0) -> 18 | AX22: =ROUND(D22*INDEX($N$19:$N$54,33),0) -> 18
A23: 2026-07-01 | B23: 1 | C23: phase_1_user_growth | D23: =ROUND(MAX(100,I23*J23*K23),0) -> 915 | E23: =MAX(0,F23-D23) -> 378 | F23: =ROUND(SUM($S$19:$S$54),0) -> 1293 | H23: =IF($B23=1,$B$6,IF($B23=2,$B$7,$B$8)) -> 0.1 | I23: =I22*(1+H23) -> 1024.87 | J23: 0.891844 | K23: =MAX(0.85,1+_xlfn.NORM.INV(RAND(),0,$B$15*0.35)) -> 1.000979 | M23: 4 | N23: =IF($M23=0,1,IF($M23=1,$B$11,IF($M23=2,$B$12,IF($M23=3,$B$13,$B$13*POWER($B$14,$M23-3)))) -> 0.0485 | S23: =ROUND(D23*INDEX($N$19:$N$54,1),0) -> 915 | T23: =ROUND(D23*INDEX($N$19:$N$54,2),0) -> 229 | U23: =ROUND(D23*INDEX($N$19:$N$54,3),0) -> 110 | V23: =ROUND(D23*INDEX($N$19:$N$54,4),0) -> 46 | W23: =ROUND(D23*INDEX($N$19:$N$54,5),0) -> 44 | X23: =ROUND(D23*INDEX($N$19:$N$54,6),0) -> 43 | Y23: =ROUND(D23*INDEX($N$19:$N$54,7),0) -> 42 | Z23: =ROUND(D23*INDEX($N$19:$N$54,8),0) -> 41 | AA23: =ROUND(D23*INDEX($N$19:$N$54,9),0) -> 39 | AB23: =ROUND(D23*INDEX($N$19:$N$54,10),0) -> 38 | AC23: =ROUND(D23*INDEX($N$19:$N$54,11),0) -> 37 | AD23: =ROUND(D23*INDEX($N$19:$N$54,12),0) -> 36 | AE23: =ROUND(D23*INDEX($N$19:$N$54,13),0) -> 35 | AF23: =ROUND(D23*INDEX($N$19:$N$54,14),0) -> 34 | AG23: =ROUND(D23*INDEX($N$19:$N$54,15),0) -> 33 | AH23: =ROUND(D23*INDEX($N$19:$N$54,16),0) -> 32 | AI23: =ROUND(D23*INDEX($N$19:$N$54,17),0) -> 31 | AJ23: =ROUND(D23*INDEX($N$19:$N$54,18),0) -> 30 | AK23: =ROUND(D23*INDEX($N$19:$N$54,19),0) -> 29 | AL23: =ROUND(D23*INDEX($N$19:$N$54,20),0) -> 28 | AM23: =ROUND(D23*INDEX($N$19:$N$54,21),0) -> 27 | AN23: =ROUND(D23*INDEX($N$19:$N$54,22),0) -> 26 | AO23: =ROUND(D23*INDEX($N$19:$N$54,23),0) -> 26 | AP23: =ROUND(D23*INDEX($N$19:$N$54,24),0) -> 25 | AQ23: =ROUND(D23*INDEX($N$19:$N$54,25),0) -> 24 | AR23: =ROUND(D23*INDEX($N$19:$N$54,26),0) -> 23 | AS23: =ROUND(D23*INDEX($N$19:$N$54,27),0) -> 23 | AT23: =ROUND(D23*INDEX($N$19:$N$54,28),0) -> 22 | AU23: =ROUND(D23*INDEX($N$19:$N$54,29),0) -> 21 | AV23: =ROUND(D23*INDEX($N$19:$N$54,30),0) -> 21 | AW23: =ROUND(D23*INDEX($N$19:$N$54,31),0) -> 20 | AX23: =ROUND(D23*INDEX($N$19:$N$54,32),0) -> 19
A24: 2026-08-01 | B24: 1 | C24: phase_1_user_growth | D24: =ROUND(MAX(100,I24*J24*K24),0) -> 1069 | E24: =MAX(0,F24-D24) -> 434 | F24: =ROUND(SUM($T$19:$T$54),0) -> 1503 | H24: =IF($B24=1,$B$6,IF($B24=2,$B$7,$B$8)) -> 0.1 | I24: =I23*(1+H24) -> 1127.36 | J24: 0.921643 | K24: =MAX(0.85,1+_xlfn.NORM.INV(RAND(),0,$B$15*0.35)) -> 1.028426 | M24: 5 | N24: =IF($M24=0,1,IF($M24=1,$B$11,IF($M24=2,$B$12,IF($M24=3,$B$13,$B$13*POWER($B$14,$M24-3)))) -> 0.047045 | T24: =ROUND(D24*INDEX($N$19:$N$54,1),0) -> 1069 | U24: =ROUND(D24*INDEX($N$19:$N$54,2),0) -> 267 | V24: =ROUND(D24*INDEX($N$19:$N$54,3),0) -> 128 | W24: =ROUND(D24*INDEX($N$19:$N$54,4),0) -> 53 | X24: =ROUND(D24*INDEX($N$19:$N$54,5),0) -> 52 | Y24: =ROUND(D24*INDEX($N$19:$N$54,6),0) -> 50 | Z24: =ROUND(D24*INDEX($N$19:$N$54,7),0) -> 49 | AA24: =ROUND(D24*INDEX($N$19:$N$54,8),0) -> 47 | AB24: =ROUND(D24*INDEX($N$19:$N$54,9),0) -> 46 | AC24: =ROUND(D24*INDEX($N$19:$N$54,10),0) -> 45 | AD24: =ROUND(D24*INDEX($N$19:$N$54,11),0) -> 43 | AE24: =ROUND(D24*INDEX($N$19:$N$54,12),0) -> 42 | AF24: =ROUND(D24*INDEX($N$19:$N$54,13),0) -> 41 | AG24: =ROUND(D24*INDEX($N$19:$N$54,14),0) -> 39 | AH24: =ROUND(D24*INDEX($N$19:$N$54,15),0) -> 38 | AI24: =ROUND(D24*INDEX($N$19:$N$54,16),0) -> 37 | AJ24: =ROUND(D24*INDEX($N$19:$N$54,17),0) -> 36 | AK24: =ROUND(D24*INDEX($N$19:$N$54,18),0) -> 35 | AL24: =ROUND(D24*INDEX($N$19:$N$54,19),0) -> 34 | AM24: =ROUND(D24*INDEX($N$19:$N$54,20),0) -> 33 | AN24: =ROUND(D24*INDEX($N$19:$N$54,21),0) -> 32 | AO24: =ROUND(D24*INDEX($N$19:$N$54,22),0) -> 31 | AP24: =ROUND(D24*INDEX($N$19:$N$54,23),0) -> 30 | AQ24: =ROUND(D24*INDEX($N$19:$N$54,24),0) -> 29 | AR24: =ROUND(D24*INDEX($N$19:$N$54,25),0) -> 28 | AS24: =ROUND(D24*INDEX($N$19:$N$54,26),0) -> 27 | AT24: =ROUND(D24*INDEX($N$19:$N$54,27),0) -> 27 | AU24: =ROUND(D24*INDEX($N$19:$N$54,28),0) -> 26 | AV24: =ROUND(D24*INDEX($N$19:$N$54,29),0) -> 25 | AW24: =ROUND(D24*INDEX($N$19:$N$54,30),0) -> 24 | AX24: =ROUND(D24*INDEX($N$19:$N$54,31),0) -> 23
A25: 2026-09-01 | B25: 1 | C25: phase_1_user_growth | D25: =ROUND(MAX(100,I25*J25*K25),0) -> 1074 | E25: =MAX(0,F25-D25) -> 519 | F25: =ROUND(SUM($U$19:$U$54),0) -> 1593 | H25: =IF($B25=1,$B$6,IF($B25=2,$B$7,$B$8)) -> 0.1 | I25: =I24*(1+H25) -> 1240.09 | J25: 0.885988 | K25: =MAX(0.85,1+_xlfn.NORM.INV(RAND(),0,$B$15*0.35)) -> 0.977212 | M25: 6 | N25: =IF($M25=0,1,IF($M25=1,$B$11,IF($M25=2,$B$12,IF($M25=3,$B$13,$B$13*POWER($B$14,$M25-3)))) -> 0.04563365 | U25: =ROUND(D25*INDEX($N$19:$N$54,1),0) -> 1074 | V25: =ROUND(D25*INDEX($N$19:$N$54,2),0) -> 268 | W25: =ROUND(D25*INDEX($N$19:$N$54,3),0) -> 129 | X25: =ROUND(D25*INDEX($N$19:$N$54,4),0) -> 54 | Y25: =ROUND(D25*INDEX($N$19:$N$54,5),0) -> 52 | Z25: =ROUND(D25*INDEX($N$19:$N$54,6),0) -> 51 | AA25: =ROUND(D25*INDEX($N$19:$N$54,7),0) -> 49 | AB25: =ROUND(D25*INDEX($N$19:$N$54,8),0) -> 48 | AC25: =ROUND(D25*INDEX($N$19:$N$54,9),0) -> 46 | AD25: =ROUND(D25*INDEX($N$19:$N$54,10),0) -> 45 | AE25: =ROUND(D25*INDEX($N$19:$N$54,11),0) -> 43 | AF25: =ROUND(D25*INDEX($N$19:$N$54,12),0) -> 42 | AG25: =ROUND(D25*INDEX($N$19:$N$54,13),0) -> 41 | AH25: =ROUND(D25*INDEX($N$19:$N$54,14),0) -> 40 | AI25: =ROUND(D25*INDEX($N$19:$N$54,15),0) -> 38 | AJ25: =ROUND(D25*INDEX($N$19:$N$54,16),0) -> 37 | AK25: =ROUND(D25*INDEX($N$19:$N$54,17),0) -> 36 | AL25: =ROUND(D25*INDEX($N$19:$N$54,18),0) -> 35 | AM25: =ROUND(D25*INDEX($N$19:$N$54,19),0) -> 34 | AN25: =ROUND(D25*INDEX($N$19:$N$54,20),0) -> 33 | AO25: =ROUND(D25*INDEX($N$19:$N$54,21),0) -> 32 | AP25: =ROUND(D25*INDEX($N$19:$N$54,22),0) -> 31 | AQ25: =ROUND(D25*INDEX($N$19:$N$54,23),0) -> 30 | AR25: =ROUND(D25*INDEX($N$19:$N$54,24),0) -> 29 | AS25: =ROUND(D25*INDEX($N$19:$N$54,25),0) -> 28 | AT25: =ROUND(D25*INDEX($N$19:$N$54,26),0) -> 27 | AU25: =ROUND(D25*INDEX($N$19:$N$54,27),0) -> 27 | AV25: =ROUND(D25*INDEX($N$19:$N$54,28),0) -> 26 | AW25: =ROUND(D25*INDEX($N$19:$N$54,29),0) -> 25 | AX25: =ROUND(D25*INDEX($N$19:$N$54,30),0) -> 24
A26: 2026-10-01 | B26: 1 | C26: phase_1_user_growth | D26: =ROUND(MAX(100,I26*J26*K26),0) -> 1244 | E26: =MAX(0,F26-D26) -> 580 | F26: =ROUND(SUM($V$19:$V$54),0) -> 1824 | H26: =IF($B26=1,$B$6,IF($B26=2,$B$7,$B$8)) -> 0.1 | I26: =I25*(1+H26) -> 1364.1 | J26: 0.911037 | K26: =MAX(0.85,1+_xlfn.NORM.INV(RAND(),0,$B$15*0.35)) -> 1.000724 | M26: 7 | N26: =IF($M26=0,1,IF($M26=1,$B$11,IF($M26=2,$B$12,IF($M26=3,$B$13,$B$13*POWER($B$14,$M26-3)))) -> 0.044264641 | V26: =ROUND(D26*INDEX($N$19:$N$54,1),0) -> 1244 | W26: =ROUND(D26*INDEX($N$19:$N$54,2),0) -> 311 | X26: =ROUND(D26*INDEX($N$19:$N$54,3),0) -> 149 | Y26: =ROUND(D26*INDEX($N$19:$N$54,4),0) -> 62 | Z26: =ROUND(D26*INDEX($N$19:$N$54,5),0) -> 60 | AA26: =ROUND(D26*INDEX($N$19:$N$54,6),0) -> 59 | AB26: =ROUND(D26*INDEX($N$19:$N$54,7),0) -> 57 | AC26: =ROUND(D26*INDEX($N$19:$N$54,8),0) -> 55 | AD26: =ROUND(D26*INDEX($N$19:$N$54,9),0) -> 53 | AE26: =ROUND(D26*INDEX($N$19:$N$54,10),0) -> 52 | AF26: =ROUND(D26*INDEX($N$19:$N$54,11),0) -> 50 | AG26: =ROUND(D26*INDEX($N$19:$N$54,12),0) -> 49 | AH26: =ROUND(D26*INDEX($N$19:$N$54,13),0) -> 47 | AI26: =ROUND(D26*INDEX($N$19:$N$54,14),0) -> 46 | AJ26: =ROUND(D26*INDEX($N$19:$N$54,15),0) -> 44 | AK26: =ROUND(D26*INDEX($N$19:$N$54,16),0) -> 43 | AL26: =ROUND(D26*INDEX($N$19:$N$54,17),0) -> 42 | AM26: =ROUND(D26*INDEX($N$19:$N$54,18),0) -> 41 | AN26: =ROUND(D26*INDEX($N$19:$N$54,19),0) -> 39 | AO26: =ROUND(D26*INDEX($N$19:$N$54,20),0) -> 38 | AP26: =ROUND(D26*INDEX($N$19:$N$54,21),0) -> 37 | AQ26: =ROUND(D26*INDEX($N$19:$N$54,22),0) -> 36 | AR26: =ROUND(D26*INDEX($N$19:$N$54,23),0) -> 35 | AS26: =ROUND(D26*INDEX($N$19:$N$54,24),0) -> 34 | AT26: =ROUND(D26*INDEX($N$19:$N$54,25),0) -> 33 | AU26: =ROUND(D26*INDEX($N$19:$N$54,26),0) -> 32 | AV26: =ROUND(D26*INDEX($N$19:$N$54,27),0) -> 31 | AW26: =ROUND(D26*INDEX($N$19:$N$54,28),0) -> 30 | AX26: =ROUND(D26*INDEX($N$19:$N$54,29),0) -> 29
A27: 2026-11-01 | B27: 1 | C27: phase_1_user_growth | D27: =ROUND(MAX(100,I27*J27*K27),0) -> 2020 | E27: =MAX(0,F27-D27) -> 671 | F27: =ROUND(SUM($W$19:$W$54),0) -> 2691 | H27: =IF($B27=1,$B$6,IF($B27=2,$B$7,$B$8)) -> 0.1 | I27: =I26*(1+H27) -> 1500.51 | J27: 1.344002 | K27: =MAX(0.85,1+_xlfn.NORM.INV(RAND(),0,$B$15*0.35)) -> 1.001745 | M27: 8 | N27: =IF($M27=0,1,IF($M27=1,$B$11,IF($M27=2,$B$12,IF($M27=3,$B$13,$B$13*POWER($B$14,$M27-3)))) -> 0.042936701 | W27: =ROUND(D27*INDEX($N$19:$N$54,1),0) -> 2020 | X27: =ROUND(D27*INDEX($N$19:$N$54,2),0) -> 505 | Y27: =ROUND(D27*INDEX($N$19:$N$54,3),0) -> 242 | Z27: =ROUND(D27*INDEX($N$19:$N$54,4),0) -> 101 | AA27: =ROUND(D27*INDEX($N$19:$N$54,5),0) -> 98 | AB27: =ROUND(D27*INDEX($N$19:$N$54,6),0) -> 95 | AC27: =ROUND(D27*INDEX($N$19:$N$54,7),0) -> 92 | AD27: =ROUND(D27*INDEX($N$19:$N$54,8),0) -> 89 | AE27: =ROUND(D27*INDEX($N$19:$N$54,9),0) -> 87 | AF27: =ROUND(D27*INDEX($N$19:$N$54,10),0) -> 84 | AG27: =ROUND(D27*INDEX($N$19:$N$54,11),0) -> 82 | AH27: =ROUND(D27*INDEX($N$19:$N$54,12),0) -> 79 | AI27: =ROUND(D27*INDEX($N$19:$N$54,13),0) -> 77 | AJ27: =ROUND(D27*INDEX($N$19:$N$54,14),0) -> 74 | AK27: =ROUND(D27*INDEX($N$19:$N$54,15),0) -> 72 | AL27: =ROUND(D27*INDEX($N$19:$N$54,16),0) -> 70 | AM27: =ROUND(D27*INDEX($N$19:$N$54,17),0) -> 68 | AN27: =ROUND(D27*INDEX($N$19:$N$54,18),0) -> 66 | AO27: =ROUND(D27*INDEX($N$19:$N$54,19),0) -> 64 | AP27: =ROUND(D27*INDEX($N$19:$N$54,20),0) -> 62 | AQ27: =ROUND(D27*INDEX($N$19:$N$54,21),0) -> 60 | AR27: =ROUND(D27*INDEX($N$19:$N$54,22),0) -> 58 | AS27: =ROUND(D27*INDEX($N$19:$N$54,23),0) -> 57 | AT27: =ROUND(D27*INDEX($N$19:$N$54,24),0) -> 55 | AU27: =ROUND(D27*INDEX($N$19:$N$54,25),0) -> 53 | AV27: =ROUND(D27*INDEX($N$19:$N$54,26),0) -> 52 | AW27: =ROUND(D27*INDEX($N$19:$N$54,27),0) -> 50 | AX27: =ROUND(D27*INDEX($N$19:$N$54,28),0) -> 49
A28: 2026-12-01 | B28: 1 | C28: phase_1_user_growth | D28: =ROUND(MAX(100,I28*J28*K28),0) -> 4065 | E28: =MAX(0,F28-D28) -> 933 | F28: =ROUND(SUM($X$19:$X$54),0) -> 4998 | H28: =IF($B28=1,$B$6,IF($B28=2,$B$7,$B$8)) -> 0.1 | I28: =I27*(1+H28) -> 1650.56 | J28: 2.521434 | K28: =MAX(0.85,1+_xlfn.NORM.INV(RAND(),0,$B$15*0.35)) -> 0.976809 | M28: 9 | N28: =IF($M28=0,1,IF($M28=1,$B$11,IF($M28=2,$B$12,IF($M28=3,$B$13,$B$13*POWER($B$14,$M28-3)))) -> 0.0416486 | X28: =ROUND(D28*INDEX($N$19:$N$54,1),0) -> 4065 | Y28: =ROUND(D28*INDEX($N$19:$N$54,2),0) -> 1016 | Z28: =ROUND(D28*INDEX($N$19:$N$54,3),0) -> 488 | AA28: =ROUND(D28*INDEX($N$19:$N$54,4),0) -> 203 | AB28: =ROUND(D28*INDEX($N$19:$N$54,5),0) -> 197 | AC28: =ROUND(D28*INDEX($N$19:$N$54,6),0) -> 191 | AD28: =ROUND(D28*INDEX($N$19:$N$54,7),0) -> 186 | AE28: =ROUND(D28*INDEX($N$19:$N$54,8),0) -> 180 | AF28: =ROUND(D28*INDEX($N$19:$N$54,9),0) -> 175 | AG28: =ROUND(D28*INDEX($N$19:$N$54,10),0) -> 169 | AH28: =ROUND(D28*INDEX($N$19:$N$54,11),0) -> 164 | AI28: =ROUND(D28*INDEX($N$19:$N$54,12),0) -> 159 | AJ28: =ROUND(D28*INDEX($N$19:$N$54,13),0) -> 155 | AK28: =ROUND(D28*INDEX($N$19:$N$54,14),0) -> 150 | AL28: =ROUND(D28*INDEX($N$19:$N$54,15),0) -> 145 | AM28: =ROUND(D28*INDEX($N$19:$N$54,16),0) -> 141 | AN28: =ROUND(D28*INDEX($N$19:$N$54,17),0) -> 137 | AO28: =ROUND(D28*INDEX($N$19:$N$54,18),0) -> 133 | AP28: =ROUND(D28*INDEX($N$19:$N$54,19),0) -> 129 | AQ28: =ROUND(D28*INDEX($N$19:$N$54,20),0) -> 125 | AR28: =ROUND(D28*INDEX($N$19:$N$54,21),0) -> 121 | AS28: =ROUND(D28*INDEX($N$19:$N$54,22),0) -> 117 | AT28: =ROUND(D28*INDEX($N$19:$N$54,23),0) -> 114 | AU28: =ROUND(D28*INDEX($N$19:$N$54,24),0) -> 111 | AV28: =ROUND(D28*INDEX($N$19:$N$54,25),0) -> 107 | AW28: =ROUND(D28*INDEX($N$19:$N$54,26),0) -> 104 | AX28: =ROUND(D28*INDEX($N$19:$N$54,27),0) -> 101
A29: 2027-01-01 | B29: 1 | C29: phase_1_user_growth | D29: =ROUND(MAX(100,I29*J29*K29),0) -> 1470 | E29: =MAX(0,F29-D29) -> 1590 | F29: =ROUND(SUM($Y$19:$Y$54),0) -> 3060 | H29: =IF($B29=1,$B$6,IF($B29=2,$B$7,$B$8)) -> 0.1 | I29: =I28*(1+H29) -> 1815.62 | J29: 0.805962 | K29: =MAX(0.85,1+_xlfn.NORM.INV(RAND(),0,$B$15*0.35)) -> 1.004354 | M29: 10 | N29: =IF($M29=0,1,IF($M29=1,$B$11,IF($M29=2,$B$12,IF($M29=3,$B$13,$B$13*POWER($B$14,$M29-3)))) -> 0.040399142 | Y29: =ROUND(D29*INDEX($N$19:$N$54,1),0) -> 1470 | Z29: =ROUND(D29*INDEX($N$19:$N$54,2),0) -> 368 | AA29: =ROUND(D29*INDEX($N$19:$N$54,3),0) -> 176 | AB29: =ROUND(D29*INDEX($N$19:$N$54,4),0) -> 74 | AC29: =ROUND(D29*INDEX($N$19:$N$54,5),0) -> 71 | AD29: =ROUND(D29*INDEX($N$19:$N$54,6),0) -> 69 | AE29: =ROUND(D29*INDEX($N$19:$N$54,7),0) -> 67 | AF29: =ROUND(D29*INDEX($N$19:$N$54,8),0) -> 65 | AG29: =ROUND(D29*INDEX($N$19:$N$54,9),0) -> 63 | AH29: =ROUND(D29*INDEX($N$19:$N$54,10),0) -> 61 | AI29: =ROUND(D29*INDEX($N$19:$N$54,11),0) -> 59 | AJ29: =ROUND(D29*INDEX($N$19:$N$54,12),0) -> 58 | AK29: =ROUND(D29*INDEX($N$19:$N$54,13),0) -> 56 | AL29: =ROUND(D29*INDEX($N$19:$N$54,14),0) -> 54 | AM29: =ROUND(D29*INDEX($N$19:$N$54,15),0) -> 53 | AN29: =ROUND(D29*INDEX($N$19:$N$54,16),0) -> 51 | AO29: =ROUND(D29*INDEX($N$19:$N$54,17),0) -> 49 | AP29: =ROUND(D29*INDEX($N$19:$N$54,18),0) -> 48 | AQ29: =ROUND(D29*INDEX($N$19:$N$54,19),0) -> 47 | AR29: =ROUND(D29*INDEX($N$19:$N$54,20),0) -> 45 | AS29: =ROUND(D29*INDEX($N$19:$N$54,21),0) -> 44 | AT29: =ROUND(D29*INDEX($N$19:$N$54,22),0) -> 42 | AU29: =ROUND(D29*INDEX($N$19:$N$54,23),0) -> 41 | AV29: =ROUND(D29*INDEX($N$19:$N$54,24),0) -> 40 | AW29: =ROUND(D29*INDEX($N$19:$N$54,25),0) -> 39 | AX29: =ROUND(D29*INDEX($N$19:$N$54,26),0) -> 38
A30: 2027-02-01 | B30: 1 | C30: phase_1_user_growth | D30: =ROUND(MAX(100,I30*J30*K30),0) -> 1974 | E30: =MAX(0,F30-D30) -> 1280 | F30: =ROUND(SUM($Z$19:$Z$54),0) -> 3254 | H30: =IF($B30=1,$B$6,IF($B30=2,$B$7,$B$8)) -> 0.1 | I30: =I29*(1+H30) -> 1997.18 | J30: 0.9952 | K30: =MAX(0.85,1+_xlfn.NORM.INV(RAND(),0,$B$15*0.35)) -> 0.993253 | M30: 11 | N30: =IF($M30=0,1,IF($M30=1,$B$11,IF($M30=2,$B$12,IF($M30=3,$B$13,$B$13*POWER($B$14,$M30-3)))) -> 0.039187168 | Z30: =ROUND(D30*INDEX($N$19:$N$54,1),0) -> 1974 | AA30: =ROUND(D30*INDEX($N$19:$N$54,2),0) -> 494 | AB30: =ROUND(D30*INDEX($N$19:$N$54,3),0) -> 237 | AC30: =ROUND(D30*INDEX($N$19:$N$54,4),0) -> 99 | AD30: =ROUND(D30*INDEX($N$19:$N$54,5),0) -> 96 | AE30: =ROUND(D30*INDEX($N$19:$N$54,6),0) -> 93 | AF30: =ROUND(D30*INDEX($N$19:$N$54,7),0) -> 90 | AG30: =ROUND(D30*INDEX($N$19:$N$54,8),0) -> 87 | AH30: =ROUND(D30*INDEX($N$19:$N$54,9),0) -> 85 | AI30: =ROUND(D30*INDEX($N$19:$N$54,10),0) -> 82 | AJ30: =ROUND(D30*INDEX($N$19:$N$54,11),0) -> 80 | AK30: =ROUND(D30*INDEX($N$19:$N$54,12),0) -> 77 | AL30: =ROUND(D30*INDEX($N$19:$N$54,13),0) -> 75 | AM30: =ROUND(D30*INDEX($N$19:$N$54,14),0) -> 73 | AN30: =ROUND(D30*INDEX($N$19:$N$54,15),0) -> 71 | AO30: =ROUND(D30*INDEX($N$19:$N$54,16),0) -> 68 | AP30: =ROUND(D30*INDEX($N$19:$N$54,17),0) -> 66 | AQ30: =ROUND(D30*INDEX($N$19:$N$54,18),0) -> 64 | AR30: =ROUND(D30*INDEX($N$19:$N$54,19),0) -> 63 | AS30: =ROUND(D30*INDEX($N$19:$N$54,20),0) -> 61 | AT30: =ROUND(D30*INDEX($N$19:$N$54,21),0) -> 59 | AU30: =ROUND(D30*INDEX($N$19:$N$54,22),0) -> 57 | AV30: =ROUND(D30*INDEX($N$19:$N$54,23),0) -> 55 | AW30: =ROUND(D30*INDEX($N$19:$N$54,24),0) -> 54 | AX30: =ROUND(D30*INDEX($N$19:$N$54,25),0) -> 52
A31: 2027-03-01 | B31: 2 | C31: phase_2_marketplace_activation | D31: =ROUND(MAX(100,I31*J31*K31),0) -> 1725 | E31: =MAX(0,F31-D31) -> 1283 | F31: =ROUND(SUM($AA$19:$AA$54),0) -> 3008 | H31: =IF($B31=1,$B$6,IF($B31=2,$B$7,$B$8)) -> 0.05 | I31: =I30*(1+H31) -> 2097.04 | J31: 0.852079 | K31: =MAX(0.85,1+_xlfn.NORM.INV(RAND(),0,$B$15*0.35)) -> 0.965491 | M31: 12 | N31: =IF($M31=0,1,IF($M31=1,$B$11,IF($M31=2,$B$12,IF($M31=3,$B$13,$B$13*POWER($B$14,$M31-3)))) -> 0.038011553 | AA31: =ROUND(D31*INDEX($N$19:$N$54,1),0) -> 1725 | AB31: =ROUND(D31*INDEX($N$19:$N$54,2),0) -> 431 | AC31: =ROUND(D31*INDEX($N$19:$N$54,3),0) -> 207 | AD31: =ROUND(D31*INDEX($N$19:$N$54,4),0) -> 86 | AE31: =ROUND(D31*INDEX($N$19:$N$54,5),0) -> 84 | AF31: =ROUND(D31*INDEX($N$19:$N$54,6),0) -> 81 | AG31: =ROUND(D31*INDEX($N$19:$N$54,7),0) -> 79 | AH31: =ROUND(D31*INDEX($N$19:$N$54,8),0) -> 76 | AI31: =ROUND(D31*INDEX($N$19:$N$54,9),0) -> 74 | AJ31: =ROUND(D31*INDEX($N$19:$N$54,10),0) -> 72 | AK31: =ROUND(D31*INDEX($N$19:$N$54,11),0) -> 70 | AL31: =ROUND(D31*INDEX($N$19:$N$54,12),0) -> 68 | AM31: =ROUND(D31*INDEX($N$19:$N$54,13),0) -> 66 | AN31: =ROUND(D31*INDEX($N$19:$N$54,14),0) -> 64 | AO31: =ROUND(D31*INDEX($N$19:$N$54,15),0) -> 62 | AP31: =ROUND(D31*INDEX($N$19:$N$54,16),0) -> 60 | AQ31: =ROUND(D31*INDEX($N$19:$N$54,17),0) -> 58 | AR31: =ROUND(D31*INDEX($N$19:$N$54,18),0) -> 56 | AS31: =ROUND(D31*INDEX($N$19:$N$54,19),0) -> 55 | AT31: =ROUND(D31*INDEX($N$19:$N$54,20),0) -> 53 | AU31: =ROUND(D31*INDEX($N$19:$N$54,21),0) -> 51 | AV31: =ROUND(D31*INDEX($N$19:$N$54,22),0) -> 50 | AW31: =ROUND(D31*INDEX($N$19:$N$54,23),0) -> 48 | AX31: =ROUND(D31*INDEX($N$19:$N$54,24),0) -> 47
A32: 2027-04-01 | B32: 2 | C32: phase_2_marketplace_activation | D32: =ROUND(MAX(100,I32*J32*K32),0) -> 1806 | E32: =MAX(0,F32-D32) -> 1338 | F32: =ROUND(SUM($AB$19:$AB$54),0) -> 3144 | H32: =IF($B32=1,$B$6,IF($B32=2,$B$7,$B$8)) -> 0.05 | I32: =I31*(1+H32) -> 2201.89 | J32: 0.843513 | K32: =MAX(0.85,1+_xlfn.NORM.INV(RAND(),0,$B$15*0.35)) -> 0.972386 | M32: 13 | N32: =IF($M32=0,1,IF($M32=1,$B$11,IF($M32=2,$B$12,IF($M32=3,$B$13,$B$13*POWER($B$14,$M32-3)))) -> 0.036871206 | AB32: =ROUND(D32*INDEX($N$19:$N$54,1),0) -> 1806 | AC32: =ROUND(D32*INDEX($N$19:$N$54,2),0) -> 452 | AD32: =ROUND(D32*INDEX($N$19:$N$54,3),0) -> 217 | AE32: =ROUND(D32*INDEX($N$19:$N$54,4),0) -> 90 | AF32: =ROUND(D32*INDEX($N$19:$N$54,5),0) -> 88 | AG32: =ROUND(D32*INDEX($N$19:$N$54,6),0) -> 85 | AH32: =ROUND(D32*INDEX($N$19:$N$54,7),0) -> 82 | AI32: =ROUND(D32*INDEX($N$19:$N$54,8),0) -> 80 | AJ32: =ROUND(D32*INDEX($N$19:$N$54,9),0) -> 78 | AK32: =ROUND(D32*INDEX($N$19:$N$54,10),0) -> 75 | AL32: =ROUND(D32*INDEX($N$19:$N$54,11),0) -> 73 | AM32: =ROUND(D32*INDEX($N$19:$N$54,12),0) -> 71 | AN32: =ROUND(D32*INDEX($N$19:$N$54,13),0) -> 69 | AO32: =ROUND(D32*INDEX($N$19:$N$54,14),0) -> 67 | AP32: =ROUND(D32*INDEX($N$19:$N$54,15),0) -> 65 | AQ32: =ROUND(D32*INDEX($N$19:$N$54,16),0) -> 63 | AR32: =ROUND(D32*INDEX($N$19:$N$54,17),0) -> 61 | AS32: =ROUND(D32*INDEX($N$19:$N$54,18),0) -> 59 | AT32: =ROUND(D32*INDEX($N$19:$N$54,19),0) -> 57 | AU32: =ROUND(D32*INDEX($N$19:$N$54,20),0) -> 55 | AV32: =ROUND(D32*INDEX($N$19:$N$54,21),0) -> 54 | AW32: =ROUND(D32*INDEX($N$19:$N$54,22),0) -> 52 | AX32: =ROUND(D32*INDEX($N$19:$N$54,23),0) -> 51
A33: 2027-05-01 | B33: 2 | C33: phase_2_marketplace_activation | D33: =ROUND(MAX(100,I33*J33*K33),0) -> 2329 | E33: =MAX(0,F33-D33) -> 1406 | F33: =ROUND(SUM($AC$19:$AC$54),0) -> 3735 | H33: =IF($B33=1,$B$6,IF($B33=2,$B$7,$B$8)) -> 0.05 | I33: =I32*(1+H33) -> 2311.99 | J33: 1.01307 | K33: =MAX(0.85,1+_xlfn.NORM.INV(RAND(),0,$B$15*0.35)) -> 0.994418 | M33: 14 | N33: =IF($M33=0,1,IF($M33=1,$B$11,IF($M33=2,$B$12,IF($M33=3,$B$13,$B$13*POWER($B$14,$M33-3)))) -> 0.03576507 | AC33: =ROUND(D33*INDEX($N$19:$N$54,1),0) -> 2329 | AD33: =ROUND(D33*INDEX($N$19:$N$54,2),0) -> 582 | AE33: =ROUND(D33*INDEX($N$19:$N$54,3),0) -> 279 | AF33: =ROUND(D33*INDEX($N$19:$N$54,4),0) -> 116 | AG33: =ROUND(D33*INDEX($N$19:$N$54,5),0) -> 113 | AH33: =ROUND(D33*INDEX($N$19:$N$54,6),0) -> 110 | AI33: =ROUND(D33*INDEX($N$19:$N$54,7),0) -> 106 | AJ33: =ROUND(D33*INDEX($N$19:$N$54,8),0) -> 103 | AK33: =ROUND(D33*INDEX($N$19:$N$54,9),0) -> 100 | AL33: =ROUND(D33*INDEX($N$19:$N$54,10),0) -> 97 | AM33: =ROUND(D33*INDEX($N$19:$N$54,11),0) -> 94 | AN33: =ROUND(D33*INDEX($N$19:$N$54,12),0) -> 91 | AO33: =ROUND(D33*INDEX($N$19:$N$54,13),0) -> 89 | AP33: =ROUND(D33*INDEX($N$19:$N$54,14),0) -> 86 | AQ33: =ROUND(D33*INDEX($N$19:$N$54,15),0) -> 83 | AR33: =ROUND(D33*INDEX($N$19:$N$54,16),0) -> 81 | AS33: =ROUND(D33*INDEX($N$19:$N$54,17),0) -> 78 | AT33: =ROUND(D33*INDEX($N$19:$N$54,18),0) -> 76 | AU33: =ROUND(D33*INDEX($N$19:$N$54,19),0) -> 74 | AV33: =ROUND(D33*INDEX($N$19:$N$54,20),0) -> 72 | AW33: =ROUND(D33*INDEX($N$19:$N$54,21),0) -> 69 | AX33: =ROUND(D33*INDEX($N$19:$N$54,22),0) -> 67
A34: 2027-06-01 | B34: 2 | C34: phase_2_marketplace_activation | D34: =ROUND(MAX(100,I34*J34*K34),0) -> 2186 | E34: =MAX(0,F34-D34) -> 1610 | F34: =ROUND(SUM($AD$19:$AD$54),0) -> 3796 | H34: =IF($B34=1,$B$6,IF($B34=2,$B$7,$B$8)) -> 0.05 | I34: =I33*(1+H34) -> 2427.59 | J34: 0.906254 | K34: =MAX(0.85,1+_xlfn.NORM.INV(RAND(),0,$B$15*0.35)) -> 0.993475 | M34: 15 | N34: =IF($M34=0,1,IF($M34=1,$B$11,IF($M34=2,$B$12,IF($M34=3,$B$13,$B$13*POWER($B$14,$M34-3)))) -> 0.034692118 | AD34: =ROUND(D34*INDEX($N$19:$N$54,1),0) -> 2186 | AE34: =ROUND(D34*INDEX($N$19:$N$54,2),0) -> 546 | AF34: =ROUND(D34*INDEX($N$19:$N$54,3),0) -> 262 | AG34: =ROUND(D34*INDEX($N$19:$N$54,4),0) -> 109 | AH34: =ROUND(D34*INDEX($N$19:$N$54,5),0) -> 106 | AI34: =ROUND(D34*INDEX($N$19:$N$54,6),0) -> 103 | AJ34: =ROUND(D34*INDEX($N$19:$N$54,7),0) -> 100 | AK34: =ROUND(D34*INDEX($N$19:$N$54,8),0) -> 97 | AL34: =ROUND(D34*INDEX($N$19:$N$54,9),0) -> 94 | AM34: =ROUND(D34*INDEX($N$19:$N$54,10),0) -> 91 | AN34: =ROUND(D34*INDEX($N$19:$N$54,11),0) -> 88 | AO34: =ROUND(D34*INDEX($N$19:$N$54,12),0) -> 86 | AP34: =ROUND(D34*INDEX($N$19:$N$54,13),0) -> 83 | AQ34: =ROUND(D34*INDEX($N$19:$N$54,14),0) -> 81 | AR34: =ROUND(D34*INDEX($N$19:$N$54,15),0) -> 78 | AS34: =ROUND(D34*INDEX($N$19:$N$54,16),0) -> 76 | AT34: =ROUND(D34*INDEX($N$19:$N$54,17),0) -> 74 | AU34: =ROUND(D34*INDEX($N$19:$N$54,18),0) -> 71 | AV34: =ROUND(D34*INDEX($N$19:$N$54,19),0) -> 69 | AW34: =ROUND(D34*INDEX($N$19:$N$54,20),0) -> 67 | AX34: =ROUND(D34*INDEX($N$19:$N$54,21),0) -> 65
A35: 2027-07-01 | B35: 2 | C35: phase_2_marketplace_activation | D35: =ROUND(MAX(100,I35*J35*K35),0) -> 2343 | E35: =MAX(0,F35-D35) -> 1703 | F35: =ROUND(SUM($AE$19:$AE$54),0) -> 4046 | H35: =IF($B35=1,$B$6,IF($B35=2,$B$7,$B$8)) -> 0.05 | I35: =I34*(1+H35) -> 2548.97 | J35: 0.891844 | K35: =MAX(0.85,1+_xlfn.NORM.INV(RAND(),0,$B$15*0.35)) -> 1.030481 | M35: 16 | N35: =IF($M35=0,1,IF($M35=1,$B$11,IF($M35=2,$B$12,IF($M35=3,$B$13,$B$13*POWER($B$14,$M35-3)))) -> 0.033651355 | AE35: =ROUND(D35*INDEX($N$19:$N$54,1),0) -> 2343 | AF35: =ROUND(D35*INDEX($N$19:$N$54,2),0) -> 586 | AG35: =ROUND(D35*INDEX($N$19:$N$54,3),0) -> 281 | AH35: =ROUND(D35*INDEX($N$19:$N$54,4),0) -> 117 | AI35: =ROUND(D35*INDEX($N$19:$N$54,5),0) -> 114 | AJ35: =ROUND(D35*INDEX($N$19:$N$54,6),0) -> 110 | AK35: =ROUND(D35*INDEX($N$19:$N$54,7),0) -> 107 | AL35: =ROUND(D35*INDEX($N$19:$N$54,8),0) -> 104 | AM35: =ROUND(D35*INDEX($N$19:$N$54,9),0) -> 101 | AN35: =ROUND(D35*INDEX($N$19:$N$54,10),0) -> 98 | AO35: =ROUND(D35*INDEX($N$19:$N$54,11),0) -> 95 | AP35: =ROUND(D35*INDEX($N$19:$N$54,12),0) -> 92 | AQ35: =ROUND(D35*INDEX($N$19:$N$54,13),0) -> 89 | AR35: =ROUND(D35*INDEX($N$19:$N$54,14),0) -> 86 | AS35: =ROUND(D35*INDEX($N$19:$N$54,15),0) -> 84 | AT35: =ROUND(D35*INDEX($N$19:$N$54,16),0) -> 81 | AU35: =ROUND(D35*INDEX($N$19:$N$54,17),0) -> 79 | AV35: =ROUND(D35*INDEX($N$19:$N$54,18),0) -> 76 | AW35: =ROUND(D35*INDEX($N$19:$N$54,19),0) -> 74 | AX35: =ROUND(D35*INDEX($N$19:$N$54,20),0) -> 72
A36: 2027-08-01 | B36: 2 | C36: phase_2_marketplace_activation | D36: =ROUND(MAX(100,I36*J36*K36),0) -> 2381 | E36: =MAX(0,F36-D36) -> 1815 | F36: =ROUND(SUM($AF$19:$AF$54),0) -> 4196 | H36: =IF($B36=1,$B$6,IF($B36=2,$B$7,$B$8)) -> 0.05 | I36: =I35*(1+H36) -> 2676.41 | J36: 0.921643 | K36: =MAX(0.85,1+_xlfn.NORM.INV(RAND(),0,$B$15*0.35)) -> 0.965328 | M36: 17 | N36: =IF($M36=0,1,IF($M36=1,$B$11,IF($M36=2,$B$12,IF($M36=3,$B$13,$B$13*POWER($B$14,$M36-3)))) -> 0.032641814 | AF36: =ROUND(D36*INDEX($N$19:$N$54,1),0) -> 2381 | AG36: =ROUND(D36*INDEX($N$19:$N$54,2),0) -> 595 | AH36: =ROUND(D36*INDEX($N$19:$N$54,3),0) -> 286 | AI36: =ROUND(D36*INDEX($N$19:$N$54,4),0) -> 119 | AJ36: =ROUND(D36*INDEX($N$19:$N$54,5),0) -> 115 | AK36: =ROUND(D36*INDEX($N$19:$N$54,6),0) -> 112 | AL36: =ROUND(D36*INDEX($N$19:$N$54,7),0) -> 109 | AM36: =ROUND(D36*INDEX($N$19:$N$54,8),0) -> 105 | AN36: =ROUND(D36*INDEX($N$19:$N$54,9),0) -> 102 | AO36: =ROUND(D36*INDEX($N$19:$N$54,10),0) -> 99 | AP36: =ROUND(D36*INDEX($N$19:$N$54,11),0) -> 96 | AQ36: =ROUND(D36*INDEX($N$19:$N$54,12),0) -> 93 | AR36: =ROUND(D36*INDEX($N$19:$N$54,13),0) -> 91 | AS36: =ROUND(D36*INDEX($N$19:$N$54,14),0) -> 88 | AT36: =ROUND(D36*INDEX($N$19:$N$54,15),0) -> 85 | AU36: =ROUND(D36*INDEX($N$19:$N$54,16),0) -> 83 | AV36: =ROUND(D36*INDEX($N$19:$N$54,17),0) -> 80 | AW36: =ROUND(D36*INDEX($N$19:$N$54,18),0) -> 78 | AX36: =ROUND(D36*INDEX($N$19:$N$54,19),0) -> 75
A37: 2027-09-01 | B37: 2 | C37: phase_2_marketplace_activation | D37: =ROUND(MAX(100,I37*J37*K37),0) -> 2478 | E37: =MAX(0,F37-D37) -> 1923 | F37: =ROUND(SUM($AG$19:$AG$54),0) -> 4401 | H37: =IF($B37=1,$B$6,IF($B37=2,$B$7,$B$8)) -> 0.05 | I37: =I36*(1+H37) -> 2810.24 | J37: 0.885988 | K37: =MAX(0.85,1+_xlfn.NORM.INV(RAND(),0,$B$15*0.35)) -> 0.995076 | M37: 18 | N37: =IF($M37=0,1,IF($M37=1,$B$11,IF($M37=2,$B$12,IF($M37=3,$B$13,$B$13*POWER($B$14,$M37-3)))) -> 0.031662559 | AG37: =ROUND(D37*INDEX($N$19:$N$54,1),0) -> 2478 | AH37: =ROUND(D37*INDEX($N$19:$N$54,2),0) -> 620 | AI37: =ROUND(D37*INDEX($N$19:$N$54,3),0) -> 297 | AJ37: =ROUND(D37*INDEX($N$19:$N$54,4),0) -> 124 | AK37: =ROUND(D37*INDEX($N$19:$N$54,5),0) -> 120 | AL37: =ROUND(D37*INDEX($N$19:$N$54,6),0) -> 117 | AM37: =ROUND(D37*INDEX($N$19:$N$54,7),0) -> 113 | AN37: =ROUND(D37*INDEX($N$19:$N$54,8),0) -> 110 | AO37: =ROUND(D37*INDEX($N$19:$N$54,9),0) -> 106 | AP37: =ROUND(D37*INDEX($N$19:$N$54,10),0) -> 103 | AQ37: =ROUND(D37*INDEX($N$19:$N$54,11),0) -> 100 | AR37: =ROUND(D37*INDEX($N$19:$N$54,12),0) -> 97 | AS37: =ROUND(D37*INDEX($N$19:$N$54,13),0) -> 94 | AT37: =ROUND(D37*INDEX($N$19:$N$54,14),0) -> 91 | AU37: =ROUND(D37*INDEX($N$19:$N$54,15),0) -> 89 | AV37: =ROUND(D37*INDEX($N$19:$N$54,16),0) -> 86 | AW37: =ROUND(D37*INDEX($N$19:$N$54,17),0) -> 83 | AX37: =ROUND(D37*INDEX($N$19:$N$54,18),0) -> 81
A38: 2027-10-01 | B38: 2 | C38: phase_2_marketplace_activation | D38: =ROUND(MAX(100,I38*J38*K38),0) -> 2739 | E38: =MAX(0,F38-D38) -> 2039 | F38: =ROUND(SUM($AH$19:$AH$54),0) -> 4778 | H38: =IF($B38=1,$B$6,IF($B38=2,$B$7,$B$8)) -> 0.05 | I38: =I37*(1+H38) -> 2950.75 | J38: 0.911037 | K38: =MAX(0.85,1+_xlfn.NORM.INV(RAND(),0,$B$15*0.35)) -> 1.018879 | M38: 19 | N38: =IF($M38=0,1,IF($M38=1,$B$11,IF($M38=2,$B$12,IF($M38=3,$B$13,$B$13*POWER($B$14,$M38-3)))) -> 0.030712683 | AH38: =ROUND(D38*INDEX($N$19:$N$54,1),0) -> 2739 | AI38: =ROUND(D38*INDEX($N$19:$N$54,2),0) -> 685 | AJ38: =ROUND(D38*INDEX($N$19:$N$54,3),0) -> 329 | AK38: =ROUND(D38*INDEX($N$19:$N$54,4),0) -> 137 | AL38: =ROUND(D38*INDEX($N$19:$N$54,5),0) -> 133 | AM38: =ROUND(D38*INDEX($N$19:$N$54,6),0) -> 129 | AN38: =ROUND(D38*INDEX($N$19:$N$54,7),0) -> 125 | AO38: =ROUND(D38*INDEX($N$19:$N$54,8),0) -> 121 | AP38: =ROUND(D38*INDEX($N$19:$N$54,9),0) -> 118 | AQ38: =ROUND(D38*INDEX($N$19:$N$54,10),0) -> 114 | AR38: =ROUND(D38*INDEX($N$19:$N$54,11),0) -> 111 | AS38: =ROUND(D38*INDEX($N$19:$N$54,12),0) -> 107 | AT38: =ROUND(D38*INDEX($N$19:$N$54,13),0) -> 104 | AU38: =ROUND(D38*INDEX($N$19:$N$54,14),0) -> 101 | AV38: =ROUND(D38*INDEX($N$19:$N$54,15),0) -> 98 | AW38: =ROUND(D38*INDEX($N$19:$N$54,16),0) -> 95 | AX38: =ROUND(D38*INDEX($N$19:$N$54,17),0) -> 92
A39: 2027-11-01 | B39: 2 | C39: phase_2_marketplace_activation | D39: =ROUND(MAX(100,I39*J39*K39),0) -> 4135 | E39: =MAX(0,F39-D39) -> 2200 | F39: =ROUND(SUM($AI$19:$AI$54),0) -> 6335 | H39: =IF($B39=1,$B$6,IF($B39=2,$B$7,$B$8)) -> 0.05 | I39: =I38*(1+H39) -> 3098.28 | J39: 1.344002 | K39: =MAX(0.85,1+_xlfn.NORM.INV(RAND(),0,$B$15*0.35)) -> 0.993049 | M39: 20 | N39: =IF($M39=0,1,IF($M39=1,$B$11,IF($M39=2,$B$12,IF($M39=3,$B$13,$B$13*POWER($B$14,$M39-3)))) -> 0.029791302 | AI39: =ROUND(D39*INDEX($N$19:$N$54,1),0) -> 4135 | AJ39: =ROUND(D39*INDEX($N$19:$N$54,2),0) -> 1034 | AK39: =ROUND(D39*INDEX($N$19:$N$54,3),0) -> 496 | AL39: =ROUND(D39*INDEX($N$19:$N$54,4),0) -> 207 | AM39: =ROUND(D39*INDEX($N$19:$N$54,5),0) -> 201 | AN39: =ROUND(D39*INDEX($N$19:$N$54,6),0) -> 195 | AO39: =ROUND(D39*INDEX($N$19:$N$54,7),0) -> 189 | AP39: =ROUND(D39*INDEX($N$19:$N$54,8),0) -> 183 | AQ39: =ROUND(D39*INDEX($N$19:$N$54,9),0) -> 178 | AR39: =ROUND(D39*INDEX($N$19:$N$54,10),0) -> 172 | AS39: =ROUND(D39*INDEX($N$19:$N$54,11),0) -> 167 | AT39: =ROUND(D39*INDEX($N$19:$N$54,12),0) -> 162 | AU39: =ROUND(D39*INDEX($N$19:$N$54,13),0) -> 157 | AV39: =ROUND(D39*INDEX($N$19:$N$54,14),0) -> 152 | AW39: =ROUND(D39*INDEX($N$19:$N$54,15),0) -> 148 | AX39: =ROUND(D39*INDEX($N$19:$N$54,16),0) -> 143
A40: 2027-12-01 | B40: 2 | C40: phase_2_marketplace_activation | D40: =ROUND(MAX(100,I40*J40*K40),0) -> 8231 | E40: =MAX(0,F40-D40) -> 2670 | F40: =ROUND(SUM($AJ$19:$AJ$54),0) -> 10901 | H40: =IF($B40=1,$B$6,IF($B40=2,$B$7,$B$8)) -> 0.05 | I40: =I39*(1+H40) -> 3253.2 | J40: 2.521434 | K40: =MAX(0.85,1+_xlfn.NORM.INV(RAND(),0,$B$15*0.35)) -> 1.003427 | M40: 21 | N40: =IF($M40=0,1,IF($M40=1,$B$11,IF($M40=2,$B$12,IF($M40=3,$B$13,$B$13*POWER($B$14,$M40-3)))) -> 0.028897563 | AJ40: =ROUND(D40*INDEX($N$19:$N$54,1),0) -> 8231 | AK40: =ROUND(D40*INDEX($N$19:$N$54,2),0) -> 2058 | AL40: =ROUND(D40*INDEX($N$19:$N$54,3),0) -> 988 | AM40: =ROUND(D40*INDEX($N$19:$N$54,4),0) -> 412 | AN40: =ROUND(D40*INDEX($N$19:$N$54,5),0) -> 399 | AO40: =ROUND(D40*INDEX($N$19:$N$54,6),0) -> 387 | AP40: =ROUND(D40*INDEX($N$19:$N$54,7),0) -> 376 | AQ40: =ROUND(D40*INDEX($N$19:$N$54,8),0) -> 364 | AR40: =ROUND(D40*INDEX($N$19:$N$54,9),0) -> 353 | AS40: =ROUND(D40*INDEX($N$19:$N$54,10),0) -> 343 | AT40: =ROUND(D40*INDEX($N$19:$N$54,11),0) -> 333 | AU40: =ROUND(D40*INDEX($N$19:$N$54,12),0) -> 323 | AV40: =ROUND(D40*INDEX($N$19:$N$54,13),0) -> 313 | AW40: =ROUND(D40*INDEX($N$19:$N$54,14),0) -> 303 | AX40: =ROUND(D40*INDEX($N$19:$N$54,15),0) -> 294
A41: 2028-01-01 | B41: 2 | C41: phase_2_marketplace_activation | D41: =ROUND(MAX(100,I41*J41*K41),0) -> 2720 | E41: =MAX(0,F41-D41) -> 3957 | F41: =ROUND(SUM($AK$19:$AK$54),0) -> 6677 | H41: =IF($B41=1,$B$6,IF($B41=2,$B$7,$B$8)) -> 0.05 | I41: =I40*(1+H41) -> 3415.86 | J41: 0.805962 | K41: =MAX(0.85,1+_xlfn.NORM.INV(RAND(),0,$B$15*0.35)) -> 0.988077 | M41: 22 | N41: =IF($M41=0,1,IF($M41=1,$B$11,IF($M41=2,$B$12,IF($M41=3,$B$13,$B$13*POWER($B$14,$M41-3)))) -> 0.028030636 | AK41: =ROUND(D41*INDEX($N$19:$N$54,1),0) -> 2720 | AL41: =ROUND(D41*INDEX($N$19:$N$54,2),0) -> 680 | AM41: =ROUND(D41*INDEX($N$19:$N$54,3),0) -> 326 | AN41: =ROUND(D41*INDEX($N$19:$N$54,4),0) -> 136 | AO41: =ROUND(D41*INDEX($N$19:$N$54,5),0) -> 132 | AP41: =ROUND(D41*INDEX($N$19:$N$54,6),0) -> 128 | AQ41: =ROUND(D41*INDEX($N$19:$N$54,7),0) -> 124 | AR41: =ROUND(D41*INDEX($N$19:$N$54,8),0) -> 120 | AS41: =ROUND(D41*INDEX($N$19:$N$54,9),0) -> 117 | AT41: =ROUND(D41*INDEX($N$19:$N$54,10),0) -> 113 | AU41: =ROUND(D41*INDEX($N$19:$N$54,11),0) -> 110 | AV41: =ROUND(D41*INDEX($N$19:$N$54,12),0) -> 107 | AW41: =ROUND(D41*INDEX($N$19:$N$54,13),0) -> 103 | AX41: =ROUND(D41*INDEX($N$19:$N$54,14),0) -> 100
A42: 2028-02-01 | B42: 2 | C42: phase_2_marketplace_activation | D42: =ROUND(MAX(100,I42*J42*K42),0) -> 3535 | E42: =MAX(0,F42-D42) -> 3238 | F42: =ROUND(SUM($AL$19:$AL$54),0) -> 6773 | H42: =IF($B42=1,$B$6,IF($B42=2,$B$7,$B$8)) -> 0.05 | I42: =I41*(1+H42) -> 3586.65 | J42: 0.9952 | K42: =MAX(0.85,1+_xlfn.NORM.INV(RAND(),0,$B$15*0.35)) -> 0.99026 | M42: 23 | N42: =IF($M42=0,1,IF($M42=1,$B$11,IF($M42=2,$B$12,IF($M42=3,$B$13,$B$13*POWER($B$14,$M42-3)))) -> 0.027189717 | AL42: =ROUND(D42*INDEX($N$19:$N$54,1),0) -> 3535 | AM42: =ROUND(D42*INDEX($N$19:$N$54,2),0) -> 884 | AN42: =ROUND(D42*INDEX($N$19:$N$54,3),0) -> 424 | AO42: =ROUND(D42*INDEX($N$19:$N$54,4),0) -> 177 | AP42: =ROUND(D42*INDEX($N$19:$N$54,5),0) -> 171 | AQ42: =ROUND(D42*INDEX($N$19:$N$54,6),0) -> 166 | AR42: =ROUND(D42*INDEX($N$19:$N$54,7),0) -> 161 | AS42: =ROUND(D42*INDEX($N$19:$N$54,8),0) -> 156 | AT42: =ROUND(D42*INDEX($N$19:$N$54,9),0) -> 152 | AU42: =ROUND(D42*INDEX($N$19:$N$54,10),0) -> 147 | AV42: =ROUND(D42*INDEX($N$19:$N$54,11),0) -> 143 | AW42: =ROUND(D42*INDEX($N$19:$N$54,12),0) -> 139 | AX42: =ROUND(D42*INDEX($N$19:$N$54,13),0) -> 134
A43: 2028-03-01 | B43: 3 | C43: phase_3_projection | D43: =ROUND(MAX(100,I43*J43*K43),0) -> 3174 | E43: =MAX(0,F43-D43) -> 3144 | F43: =ROUND(SUM($AM$19:$AM$54),0) -> 6318 | H43: =IF($B43=1,$B$6,IF($B43=2,$B$7,$B$8)) -> 0.03 | I43: =I42*(1+H43) -> 3694.25 | J43: 0.852079 | K43: =MAX(0.85,1+_xlfn.NORM.INV(RAND(),0,$B$15*0.35)) -> 1.008368 | M43: 24 | N43: =IF($M43=0,1,IF($M43=1,$B$11,IF($M43=2,$B$12,IF($M43=3,$B$13,$B$13*POWER($B$14,$M43-3)))) -> 0.026374026 | AM43: =ROUND(D43*INDEX($N$19:$N$54,1),0) -> 3174 | AN43: =ROUND(D43*INDEX($N$19:$N$54,2),0) -> 794 | AO43: =ROUND(D43*INDEX($N$19:$N$54,3),0) -> 381 | AP43: =ROUND(D43*INDEX($N$19:$N$54,4),0) -> 159 | AQ43: =ROUND(D43*INDEX($N$19:$N$54,5),0) -> 154 | AR43: =ROUND(D43*INDEX($N$19:$N$54,6),0) -> 149 | AS43: =ROUND(D43*INDEX($N$19:$N$54,7),0) -> 145 | AT43: =ROUND(D43*INDEX($N$19:$N$54,8),0) -> 140 | AU43: =ROUND(D43*INDEX($N$19:$N$54,9),0) -> 136 | AV43: =ROUND(D43*INDEX($N$19:$N$54,10),0) -> 132 | AW43: =ROUND(D43*INDEX($N$19:$N$54,11),0) -> 128 | AX43: =ROUND(D43*INDEX($N$19:$N$54,12),0) -> 124
A44: 2028-04-01 | B44: 3 | C44: phase_3_projection | D44: =ROUND(MAX(100,I44*J44*K44),0) -> 3285 | E44: =MAX(0,F44-D44) -> 3231 | F44: =ROUND(SUM($AN$19:$AN$54),0) -> 6516 | H44: =IF($B44=1,$B$6,IF($B44=2,$B$7,$B$8)) -> 0.03 | I44: =I43*(1+H44) -> 3805.08 | J44: 0.843513 | K44: =MAX(0.85,1+_xlfn.NORM.INV(RAND(),0,$B$15*0.35)) -> 1.023444 | M44: 25 | N44: =IF($M44=0,1,IF($M44=1,$B$11,IF($M44=2,$B$12,IF($M44=3,$B$13,$B$13*POWER($B$14,$M44-3)))) -> 0.025582805 | AN44: =ROUND(D44*INDEX($N$19:$N$54,1),0) -> 3285 | AO44: =ROUND(D44*INDEX($N$19:$N$54,2),0) -> 821 | AP44: =ROUND(D44*INDEX($N$19:$N$54,3),0) -> 394 | AQ44: =ROUND(D44*INDEX($N$19:$N$54,4),0) -> 164 | AR44: =ROUND(D44*INDEX($N$19:$N$54,5),0) -> 159 | AS44: =ROUND(D44*INDEX($N$19:$N$54,6),0) -> 155 | AT44: =ROUND(D44*INDEX($N$19:$N$54,7),0) -> 150 | AU44: =ROUND(D44*INDEX($N$19:$N$54,8),0) -> 145 | AV44: =ROUND(D44*INDEX($N$19:$N$54,9),0) -> 141 | AW44: =ROUND(D44*INDEX($N$19:$N$54,10),0) -> 137 | AX44: =ROUND(D44*INDEX($N$19:$N$54,11),0) -> 133
A45: 2028-05-01 | B45: 3 | C45: phase_3_projection | D45: =ROUND(MAX(100,I45*J45*K45),0) -> 4025 | E45: =MAX(0,F45-D45) -> 3330 | F45: =ROUND(SUM($AO$19:$AO$54),0) -> 7355 | H45: =IF($B45=1,$B$6,IF($B45=2,$B$7,$B$8)) -> 0.03 | I45: =I44*(1+H45) -> 3919.23 | J45: 1.01307 | K45: =MAX(0.85,1+_xlfn.NORM.INV(RAND(),0,$B$15*0.35)) -> 1.013624 | M45: 26 | N45: =IF($M45=0,1,IF($M45=1,$B$11,IF($M45=2,$B$12,IF($M45=3,$B$13,$B$13*POWER($B$14,$M45-3)))) -> 0.024815321 | AO45: =ROUND(D45*INDEX($N$19:$N$54,1),0) -> 4025 | AP45: =ROUND(D45*INDEX($N$19:$N$54,2),0) -> 1006 | AQ45: =ROUND(D45*INDEX($N$19:$N$54,3),0) -> 483 | AR45: =ROUND(D45*INDEX($N$19:$N$54,4),0) -> 201 | AS45: =ROUND(D45*INDEX($N$19:$N$54,5),0) -> 195 | AT45: =ROUND(D45*INDEX($N$19:$N$54,6),0) -> 189 | AU45: =ROUND(D45*INDEX($N$19:$N$54,7),0) -> 184 | AV45: =ROUND(D45*INDEX($N$19:$N$54,8),0) -> 178 | AW45: =ROUND(D45*INDEX($N$19:$N$54,9),0) -> 173 | AX45: =ROUND(D45*INDEX($N$19:$N$54,10),0) -> 168
A46: 2028-06-01 | B46: 3 | C46: phase_3_projection | D46: =ROUND(MAX(100,I46*J46*K46),0) -> 3588 | E46: =MAX(0,F46-D46) -> 3623 | F46: =ROUND(SUM($AP$19:$AP$54),0) -> 7211 | H46: =IF($B46=1,$B$6,IF($B46=2,$B$7,$B$8)) -> 0.03 | I46: =I45*(1+H46) -> 4036.81 | J46: 0.906254 | K46: =MAX(0.85,1+_xlfn.NORM.INV(RAND(),0,$B$15*0.35)) -> 0.9807 | M46: 27 | N46: =IF($M46=0,1,IF($M46=1,$B$11,IF($M46=2,$B$12,IF($M46=3,$B$13,$B$13*POWER($B$14,$M46-3)))) -> 0.024070861 | AP46: =ROUND(D46*INDEX($N$19:$N$54,1),0) -> 3588 | AQ46: =ROUND(D46*INDEX($N$19:$N$54,2),0) -> 897 | AR46: =ROUND(D46*INDEX($N$19:$N$54,3),0) -> 431 | AS46: =ROUND(D46*INDEX($N$19:$N$54,4),0) -> 179 | AT46: =ROUND(D46*INDEX($N$19:$N$54,5),0) -> 174 | AU46: =ROUND(D46*INDEX($N$19:$N$54,6),0) -> 169 | AV46: =ROUND(D46*INDEX($N$19:$N$54,7),0) -> 164 | AW46: =ROUND(D46*INDEX($N$19:$N$54,8),0) -> 159 | AX46: =ROUND(D46*INDEX($N$19:$N$54,9),0) -> 154
A47: 2028-07-01 | B47: 3 | C47: phase_3_projection | D47: =ROUND(MAX(100,I47*J47*K47),0) -> 3723 | E47: =MAX(0,F47-D47) -> 3699 | F47: =ROUND(SUM($AQ$19:$AQ$54),0) -> 7422 | H47: =IF($B47=1,$B$6,IF($B47=2,$B$7,$B$8)) -> 0.03 | I47: =I46*(1+H47) -> 4157.91 | J47: 0.891844 | K47: =MAX(0.85,1+_xlfn.NORM.INV(RAND(),0,$B$15*0.35)) -> 1.004065 | M47: 28 | N47: =IF($M47=0,1,IF($M47=1,$B$11,IF($M47=2,$B$12,IF($M47=3,$B$13,$B$13*POWER($B$14,$M47-3)))) -> 0.023348735 | AQ47: =ROUND(D47*INDEX($N$19:$N$54,1),0) -> 3723 | AR47: =ROUND(D47*INDEX($N$19:$N$54,2),0) -> 931 | AS47: =ROUND(D47*INDEX($N$19:$N$54,3),0) -> 447 | AT47: =ROUND(D47*INDEX($N$19:$N$54,4),0) -> 186 | AU47: =ROUND(D47*INDEX($N$19:$N$54,5),0) -> 181 | AV47: =ROUND(D47*INDEX($N$19:$N$54,6),0) -> 175 | AW47: =ROUND(D47*INDEX($N$19:$N$54,7),0) -> 170 | AX47: =ROUND(D47*INDEX($N$19:$N$54,8),0) -> 165
A48: 2028-08-01 | B48: 3 | C48: phase_3_projection | D48: =ROUND(MAX(100,I48*J48*K48),0) -> 3843 | E48: =MAX(0,F48-D48) -> 3811 | F48: =ROUND(SUM($AR$19:$AR$54),0) -> 7654 | H48: =IF($B48=1,$B$6,IF($B48=2,$B$7,$B$8)) -> 0.03 | I48: =I47*(1+H48) -> 4282.65 | J48: 0.921643 | K48: =MAX(0.85,1+_xlfn.NORM.INV(RAND(),0,$B$15*0.35)) -> 0.973585 | M48: 29 | N48: =IF($M48=0,1,IF($M48=1,$B$11,IF($M48=2,$B$12,IF($M48=3,$B$13,$B$13*POWER($B$14,$M48-3)))) -> 0.022648273 | AR48: =ROUND(D48*INDEX($N$19:$N$54,1),0) -> 3843 | AS48: =ROUND(D48*INDEX($N$19:$N$54,2),0) -> 961 | AT48: =ROUND(D48*INDEX($N$19:$N$54,3),0) -> 461 | AU48: =ROUND(D48*INDEX($N$19:$N$54,4),0) -> 192 | AV48: =ROUND(D48*INDEX($N$19:$N$54,5),0) -> 186 | AW48: =ROUND(D48*INDEX($N$19:$N$54,6),0) -> 181 | AX48: =ROUND(D48*INDEX($N$19:$N$54,7),0) -> 175
A49: 2028-09-01 | B49: 3 | C49: phase_3_projection | D49: =ROUND(MAX(100,I49*J49*K49),0) -> 3741 | E49: =MAX(0,F49-D49) -> 3964 | F49: =ROUND(SUM($AS$19:$AS$54),0) -> 7705 | H49: =IF($B49=1,$B$6,IF($B49=2,$B$7,$B$8)) -> 0.03 | I49: =I48*(1+H49) -> 4411.13 | J49: 0.885988 | K49: =MAX(0.85,1+_xlfn.NORM.INV(RAND(),0,$B$15*0.35)) -> 0.957291 | M49: 30 | N49: =IF($M49=0,1,IF($M49=1,$B$11,IF($M49=2,$B$12,IF($M49=3,$B$13,$B$13*POWER($B$14,$M49-3)))) -> 0.021968825 | AS49: =ROUND(D49*INDEX($N$19:$N$54,1),0) -> 3741 | AT49: =ROUND(D49*INDEX($N$19:$N$54,2),0) -> 935 | AU49: =ROUND(D49*INDEX($N$19:$N$54,3),0) -> 449 | AV49: =ROUND(D49*INDEX($N$19:$N$54,4),0) -> 187 | AW49: =ROUND(D49*INDEX($N$19:$N$54,5),0) -> 181 | AX49: =ROUND(D49*INDEX($N$19:$N$54,6),0) -> 176
A50: 2028-10-01 | B50: 3 | C50: phase_3_projection | D50: =ROUND(MAX(100,I50*J50*K50),0) -> 4128 | E50: =MAX(0,F50-D50) -> 4062 | F50: =ROUND(SUM($AT$19:$AT$54),0) -> 8190 | H50: =IF($B50=1,$B$6,IF($B50=2,$B$7,$B$8)) -> 0.03 | I50: =I49*(1+H50) -> 4543.46 | J50: 0.911037 | K50: =MAX(0.85,1+_xlfn.NORM.INV(RAND(),0,$B$15*0.35)) -> 0.997166 | M50: 31 | N50: =IF($M50=0,1,IF($M50=1,$B$11,IF($M50=2,$B$12,IF($M50=3,$B$13,$B$13*POWER($B$14,$M50-3)))) -> 0.02130976 | AT50: =ROUND(D50*INDEX($N$19:$N$54,1),0) -> 4128 | AU50: =ROUND(D50*INDEX($N$19:$N$54,2),0) -> 1032 | AV50: =ROUND(D50*INDEX($N$19:$N$54,3),0) -> 495 | AW50: =ROUND(D50*INDEX($N$19:$N$54,4),0) -> 206 | AX50: =ROUND(D50*INDEX($N$19:$N$54,5),0) -> 200
A51: 2028-11-01 | B51: 3 | C51: phase_3_projection | D51: =ROUND(MAX(100,I51*J51*K51),0) -> 6314 | E51: =MAX(0,F51-D51) -> 4261 | F51: =ROUND(SUM($AU$19:$AU$54),0) -> 10575 | H51: =IF($B51=1,$B$6,IF($B51=2,$B$7,$B$8)) -> 0.03 | I51: =I50*(1+H51) -> 4679.77 | J51: 1.344002 | K51: =MAX(0.85,1+_xlfn.NORM.INV(RAND(),0,$B$15*0.35)) -> 1.003822 | M51: 32 | N51: =IF($M51=0,1,IF($M51=1,$B$11,IF($M51=2,$B$12,IF($M51=3,$B$13,$B$13*POWER($B$14,$M51-3)))) -> 0.020670467 | AU51: =ROUND(D51*INDEX($N$19:$N$54,1),0) -> 6314 | AV51: =ROUND(D51*INDEX($N$19:$N$54,2),0) -> 1578 | AW51: =ROUND(D51*INDEX($N$19:$N$54,3),0) -> 758 | AX51: =ROUND(D51*INDEX($N$19:$N$54,4),0) -> 316
A52: 2028-12-01 | B52: 3 | C52: phase_3_projection | D52: =ROUND(MAX(100,I52*J52*K52),0) -> 11880 | E52: =MAX(0,F52-D52) -> 4955 | F52: =ROUND(SUM($AV$19:$AV$54),0) -> 16835 | H52: =IF($B52=1,$B$6,IF($B52=2,$B$7,$B$8)) -> 0.03 | I52: =I51*(1+H52) -> 4820.16 | J52: 2.521434 | K52: =MAX(0.85,1+_xlfn.NORM.INV(RAND(),0,$B$15*0.35)) -> 0.977494 | M52: 33 | N52: =IF($M52=0,1,IF($M52=1,$B$11,IF($M52=2,$B$12,IF($M52=3,$B$13,$B$13*POWER($B$14,$M52-3)))) -> 0.020050353 | AV52: =ROUND(D52*INDEX($N$19:$N$54,1),0) -> 11880 | AW52: =ROUND(D52*INDEX($N$19:$N$54,2),0) -> 2970 | AX52: =ROUND(D52*INDEX($N$19:$N$54,3),0) -> 1426
A53: 2029-01-01 | B53: 3 | C53: phase_3_projection | D53: =ROUND(MAX(100,I53*J53*K53),0) -> 3968 | E53: =MAX(0,F53-D53) -> 6729 | F53: =ROUND(SUM($AW$19:$AW$54),0) -> 10697 | H53: =IF($B53=1,$B$6,IF($B53=2,$B$7,$B$8)) -> 0.03 | I53: =I52*(1+H53) -> 4964.76 | J53: 0.805962 | K53: =MAX(0.85,1+_xlfn.NORM.INV(RAND(),0,$B$15*0.35)) -> 0.991632 | M53: 34 | N53: =IF($M53=0,1,IF($M53=1,$B$11,IF($M53=2,$B$12,IF($M53=3,$B$13,$B$13*POWER($B$14,$M53-3)))) -> 0.019448843 | AW53: =ROUND(D53*INDEX($N$19:$N$54,1),0) -> 3968 | AX53: =ROUND(D53*INDEX($N$19:$N$54,2),0) -> 992
A54: 2029-02-01 | B54: 3 | C54: phase_3_projection | D54: =ROUND(MAX(100,I54*J54*K54),0) -> 5144 | E54: =MAX(0,F54-D54) -> 5644 | F54: =ROUND(SUM($AX$19:$AX$54),0) -> 10788 | H54: =IF($B54=1,$B$6,IF($B54=2,$B$7,$B$8)) -> 0.03 | I54: =I53*(1+H54) -> 5113.71 | J54: 0.9952 | K54: =MAX(0.85,1+_xlfn.NORM.INV(RAND(),0,$B$15*0.35)) -> 1.010854 | M54: 35 | N54: =IF($M54=0,1,IF($M54=1,$B$11,IF($M54=2,$B$12,IF($M54=3,$B$13,$B$13*POWER($B$14,$M54-3)))) -> 0.018865378 | AX54: =ROUND(D54*INDEX($N$19:$N$54,1),0) -> 5144

Sheet Subscriptions
A1: [Subscriptions Assumptions] | C1: Inputs used by the subscription revenue projection below.
A2: name | B2: value | C2: details
A3: projection_months | B3: 36 | C3: Number of projected monthly rows in the workbook model.
A4: projection_start_month | B4: 2026-03 | C4: First month of the synthetic projection in YYYY-MM format.
A5: subscription_conversion_start | B5: 0.008 | C5: Initial MAU-to-paid conversion rate.
A6: subscription_conversion_end | B6: 0.025 | C6: Target MAU-to-paid conversion rate approached over time.
A7: subscription_conversion_monthly_improvement_rate | B7: 0.08 | C7: Share of the remaining conversion-rate gap closed each month.
A8: subscription_retention_start | B8: 0.3 | C8: Initial monthly subscriber retention rate.
A9: subscription_retention_end | B9: 0.6 | C9: Target monthly subscriber retention rate approached over time.
A10: subscription_retention_monthly_improvement_rate | B10: 0.06 | C10: Share of the remaining retention-rate gap closed each month.
A11: subscription_price_usd | B11: 20 | C11: Monthly subscription price used by the Subscriptions sheet.
A12: dependency | B12: MAU.mau | C12: Subscriber-state and subscription revenue are derived from the MAU sheet's audience base.
A14: month | B14: year_index | C14: phase | D14: mau | E14: subscription_conversion_rate | F14: subscription_retention_rate | G14: retained_subscribers | H14: new_subscribers | I14: churned_subscribers | J14: active_subscribers | K14: subscription_price_usd | L14: subscription_revenue_usd
A15: 2026-03-01 | B15: 1 | C15: phase_1_user_growth | D15: ='MAU'!$F19 -> 613 | E15: =$B$5 -> 0.008 | F15: =$B$8 -> 0.3 | G15: =ROUND(IF(ROW()=15,0,J14)*F15,0) -> 0 | H15: =ROUND(MAX(0,J15-G15),0) -> 5 | I15: =ROUND(MAX(0,IF(ROW()=15,0,J14)-G15),0) -> 0 | J15: =ROUND(MAX(G15,D15*E15),0) -> 5 | K15: =$B$11 -> 20 | L15: =ROUND(J15*K15,2) -> 100
A16: 2026-04-01 | B16: 1 | C16: phase_1_user_growth | D16: ='MAU'!$F20 -> 790 | E16: =E15+($B$6-E15)*$B$7 -> 0.0094 | F16: =F15+($B$9-F15)*$B$10 -> 0.318 | G16: =ROUND(IF(ROW()=15,0,J15)*F16,0) -> 2 | H16: =ROUND(MAX(0,J16-G16),0) -> 6 | I16: =ROUND(MAX(0,IF(ROW()=15,0,J15)-G16),0) -> 3 | J16: =ROUND(MAX(G16,D16*E16),0) -> 7 | K16: =$B$11 -> 20 | L16: =ROUND(J16*K16,2) -> 140
A17: 2026-05-01 | B17: 1 | C17: phase_1_user_growth | D17: ='MAU'!$F21 -> 1101 | E17: =E16+($B$6-E16)*$B$7 -> 0.0106 | F17: =F16+($B$9-F16)*$B$10 -> 0.3349 | G17: =ROUND(IF(ROW()=15,0,J16)*F17,0) -> 2 | H17: =ROUND(MAX(0,J17-G17),0) -> 9 | I17: =ROUND(MAX(0,IF(ROW()=15,0,J16)-G17),0) -> 5 | J17: =ROUND(MAX(G17,D17*E17),0) -> 12 | K17: =$B$11 -> 20 | L17: =ROUND(J17*K17,2) -> 240
A18: 2026-06-01 | B18: 1 | C18: phase_1_user_growth | D18: ='MAU'!$F22 -> 1171 | E18: =E17+($B$6-E17)*$B$7 -> 0.0118 | F18: =F17+($B$9-F17)*$B$10 -> 0.3508 | G18: =ROUND(IF(ROW()=15,0,J17)*F18,0) -> 4 | H18: =ROUND(MAX(0,J18-G18),0) -> 10 | I18: =ROUND(MAX(0,IF(ROW()=15,0,J17)-G18),0) -> 8 | J18: =ROUND(MAX(G18,D18*E18),0) -> 14 | K18: =$B$11 -> 20 | L18: =ROUND(J18*K18,2) -> 280
A19: 2026-07-01 | B19: 1 | C19: phase_1_user_growth | D19: ='MAU'!$F23 -> 1293 | E19: =E18+($B$6-E18)*$B$7 -> 0.0128 | F19: =F18+($B$9-F18)*$B$10 -> 0.3658 | G19: =ROUND(IF(ROW()=15,0,J18)*F19,0) -> 5 | H19: =ROUND(MAX(0,J19-G19),0) -> 12 | I19: =ROUND(MAX(0,IF(ROW()=15,0,J18)-G19),0) -> 9 | J19: =ROUND(MAX(G19,D19*E19),0) -> 17 | K19: =$B$11 -> 20 | L19: =ROUND(J19*K19,2) -> 340
A20: 2026-08-01 | B20: 1 | C20: phase_1_user_growth | D20: ='MAU'!$F24 -> 1503 | E20: =E19+($B$6-E19)*$B$7 -> 0.0138 | F20: =F19+($B$9-F19)*$B$10 -> 0.3798 | G20: =ROUND(IF(ROW()=15,0,J19)*F20,0) -> 6 | H20: =ROUND(MAX(0,J20-G20),0) -> 14 | I20: =ROUND(MAX(0,IF(ROW()=15,0,J19)-G20),0) -> 10 | J20: =ROUND(MAX(G20,D20*E20),0) -> 21 | K20: =$B$11 -> 20 | L20: =ROUND(J20*K20,2) -> 420
A21: 2026-09-01 | B21: 1 | C21: phase_1_user_growth | D21: ='MAU'!$F25 -> 1593 | E21: =E20+($B$6-E20)*$B$7 -> 0.0147 | F21: =F20+($B$9-F20)*$B$10 -> 0.393 | G21: =ROUND(IF(ROW()=15,0,J20)*F21,0) -> 8 | H21: =ROUND(MAX(0,J21-G21),0) -> 15 | I21: =ROUND(MAX(0,IF(ROW()=15,0,J20)-G21),0) -> 13 | J21: =ROUND(MAX(G21,D21*E21),0) -> 23 | K21: =$B$11 -> 20 | L21: =ROUND(J21*K21,2) -> 460
A22: 2026-10-01 | B22: 1 | C22: phase_1_user_growth | D22: ='MAU'!$F26 -> 1824 | E22: =E21+($B$6-E21)*$B$7 -> 0.0155 | F22: =F21+($B$9-F21)*$B$10 -> 0.4055 | G22: =ROUND(IF(ROW()=15,0,J21)*F22,0) -> 9 | H22: =ROUND(MAX(0,J22-G22),0) -> 19 | I22: =ROUND(MAX(0,IF(ROW()=15,0,J21)-G22),0) -> 14 | J22: =ROUND(MAX(G22,D22*E22),0) -> 28 | K22: =$B$11 -> 20 | L22: =ROUND(J22*K22,2) -> 560
A23: 2026-11-01 | B23: 1 | C23: phase_1_user_growth | D23: ='MAU'!$F27 -> 2691 | E23: =E22+($B$6-E22)*$B$7 -> 0.0163 | F23: =F22+($B$9-F22)*$B$10 -> 0.4171 | G23: =ROUND(IF(ROW()=15,0,J22)*F23,0) -> 12 | H23: =ROUND(MAX(0,J23-G23),0) -> 32 | I23: =ROUND(MAX(0,IF(ROW()=15,0,J22)-G23),0) -> 16 | J23: =ROUND(MAX(G23,D23*E23),0) -> 44 | K23: =$B$11 -> 20 | L23: =ROUND(J23*K23,2) -> 880
A24: 2026-12-01 | B24: 1 | C24: phase_1_user_growth | D24: ='MAU'!$F28 -> 4998 | E24: =E23+($B$6-E23)*$B$7 -> 0.017 | F24: =F23+($B$9-F23)*$B$10 -> 0.4281 | G24: =ROUND(IF(ROW()=15,0,J23)*F24,0) -> 19 | H24: =ROUND(MAX(0,J24-G24),0) -> 66 | I24: =ROUND(MAX(0,IF(ROW()=15,0,J23)-G24),0) -> 25 | J24: =ROUND(MAX(G24,D24*E24),0) -> 85 | K24: =$B$11 -> 20 | L24: =ROUND(J24*K24,2) -> 1700
A25: 2027-01-01 | B25: 1 | C25: phase_1_user_growth | D25: ='MAU'!$F29 -> 3060 | E25: =E24+($B$6-E24)*$B$7 -> 0.0176 | F25: =F24+($B$9-F24)*$B$10 -> 0.4384 | G25: =ROUND(IF(ROW()=15,0,J24)*F25,0) -> 37 | H25: =ROUND(MAX(0,J25-G25),0) -> 17 | I25: =ROUND(MAX(0,IF(ROW()=15,0,J24)-G25),0) -> 48 | J25: =ROUND(MAX(G25,D25*E25),0) -> 54 | K25: =$B$11 -> 20 | L25: =ROUND(J25*K25,2) -> 1080
A26: 2027-02-01 | B26: 1 | C26: phase_1_user_growth | D26: ='MAU'!$F30 -> 3254 | E26: =E25+($B$6-E25)*$B$7 -> 0.0182 | F26: =F25+($B$9-F25)*$B$10 -> 0.4481 | G26: =ROUND(IF(ROW()=15,0,J25)*F26,0) -> 24 | H26: =ROUND(MAX(0,J26-G26),0) -> 35 | I26: =ROUND(MAX(0,IF(ROW()=15,0,J25)-G26),0) -> 30 | J26: =ROUND(MAX(G26,D26*E26),0) -> 59 | K26: =$B$11 -> 20 | L26: =ROUND(J26*K26,2) -> 1180
A27: 2027-03-01 | B27: 2 | C27: phase_2_marketplace_activation | D27: ='MAU'!$F31 -> 3008 | E27: =E26+($B$6-E26)*$B$7 -> 0.0187 | F27: =F26+($B$9-F26)*$B$10 -> 0.4572 | G27: =ROUND(IF(ROW()=15,0,J26)*F27,0) -> 27 | H27: =ROUND(MAX(0,J27-G27),0) -> 29 | I27: =ROUND(MAX(0,IF(ROW()=15,0,J26)-G27),0) -> 32 | J27: =ROUND(MAX(G27,D27*E27),0) -> 56 | K27: =$B$11 -> 20 | L27: =ROUND(J27*K27,2) -> 1120
... A50: 2029-02-01 | B50: 3 | C50: phase_3_projection | D50: ='MAU'!$F54 -> 10788 | E50: =E49+($B$6-E49)*$B$7 -> 0.0241 | F50: =F49+($B$9-F49)*$B$10 -> 0.5656 | G50: =ROUND(IF(ROW()=15,0,J49)*F50,0) -> 145 | H50: =ROUND(MAX(0,J50-G50),0) -> 115 | I50: =ROUND(MAX(0,IF(ROW()=15,0,J49)-G50),0) -> 112 | J50: =ROUND(MAX(G50,D50*E50),0) -> 260 | K50: =$B$11 -> 20 | L50: =ROUND(J50*K50,2) -> 5200

Sheet Ads
A1: [Ads Assumptions] | C1: Inputs used by the ad revenue projection below.
A2: name | B2: value | C2: details
A3: projection_months | B3: 36 | C3: Number of projected monthly rows in the workbook model.
A4: projection_start_month | B4: 2026-03 | C4: First month of the synthetic projection in YYYY-MM format.
A5: sessions_per_mau | B5: 3 | C5: Monthly sessions generated by each monthly active user.
A6: pageviews_per_session | B6: 5 | C6: Average pageviews generated in each session.
A7: ad_action_rate_per_pageview | B7: 0.003 | C7: Share of pageviews that convert into a CPA-qualified action.
A8: ad_cpa_usd | B8: 3 | C8: CPA payout in USD for each modeled ad action.
A9: jitter_std | B9: 0.05 | C9: Standard deviation used by the random-driver formulas.
A10: dependency | B10: MAU.mau | C10: Ad calculations are derived from MAU, sessions, and pageviews.
A12: month | B12: year_index | C12: phase | D12: sessions_per_mau | E12: pageviews_per_session | F12: sessions | G12: pageviews | H12: ad_action_rate_per_pageview | I12: noise_ad | J12: ad_actions | K12: ad_cpa_usd | L12: ad_revenue_usd
A13: 2026-03-01 | B13: 1 | C13: phase_1_user_growth | D13: =$B$5 -> 3 | E13: =$B$6 -> 5 | F13: =ROUND('MAU'!$F19*D13,0) -> 1839 | G13: =ROUND(F13*E13,0) -> 9195 | H13: =$B$7 -> 0.003 | I13: =MAX(0.8,1+_xlfn.NORM.INV(RAND(),0,$B$9*0.3)) -> 1.024946 | J13: =ROUND(G13*H13*I13,0) -> 28 | K13: =$B$8 -> 3 | L13: =ROUND(J13*K13,2) -> 84.82
A14: 2026-04-01 | B14: 1 | C14: phase_1_user_growth | D14: =$B$5 -> 3 | E14: =$B$6 -> 5 | F14: =ROUND('MAU'!$F20*D14,0) -> 2370 | G14: =ROUND(F14*E14,0) -> 11850 | H14: =$B$7 -> 0.003 | I14: =MAX(0.8,1+_xlfn.NORM.INV(RAND(),0,$B$9*0.3)) -> 0.991229 | J14: =ROUND(G14*H14*I14,0) -> 35 | K14: =$B$8 -> 3 | L14: =ROUND(J14*K14,2) -> 105.71
A15: 2026-05-01 | B15: 1 | C15: phase_1_user_growth | D15: =$B$5 -> 3 | E15: =$B$6 -> 5 | F15: =ROUND('MAU'!$F21*D15,0) -> 3303 | G15: =ROUND(F15*E15,0) -> 16515 | H15: =$B$7 -> 0.003 | I15: =MAX(0.8,1+_xlfn.NORM.INV(RAND(),0,$B$9*0.3)) -> 0.993722 | J15: =ROUND(G15*H15*I15,0) -> 49 | K15: =$B$8 -> 3 | L15: =ROUND(J15*K15,2) -> 147.7
A16: 2026-06-01 | B16: 1 | C16: phase_1_user_growth | D16: =$B$5 -> 3 | E16: =$B$6 -> 5 | F16: =ROUND('MAU'!$F22*D16,0) -> 3513 | G16: =ROUND(F16*E16,0) -> 17565 | H16: =$B$7 -> 0.003 | I16: =MAX(0.8,1+_xlfn.NORM.INV(RAND(),0,$B$9*0.3)) -> 0.986639 | J16: =ROUND(G16*H16*I16,0) -> 52 | K16: =$B$8 -> 3 | L16: =ROUND(J16*K16,2) -> 155.97
A17: 2026-07-01 | B17: 1 | C17: phase_1_user_growth | D17: =$B$5 -> 3 | E17: =$B$6 -> 5 | F17: =ROUND('MAU'!$F23*D17,0) -> 3879 | G17: =ROUND(F17*E17,0) -> 19395 | H17: =$B$7 -> 0.003 | I17: =MAX(0.8,1+_xlfn.NORM.INV(RAND(),0,$B$9*0.3)) -> 0.995143 | J17: =ROUND(G17*H17*I17,0) -> 58 | K17: =$B$8 -> 3 | L17: =ROUND(J17*K17,2) -> 173.71
A18: 2026-08-01 | B18: 1 | C18: phase_1_user_growth | D18: =$B$5 -> 3 | E18: =$B$6 -> 5 | F18: =ROUND('MAU'!$F24*D18,0) -> 4509 | G18: =ROUND(F18*E18,0) -> 22545 | H18: =$B$7 -> 0.003 | I18: =MAX(0.8,1+_xlfn.NORM.INV(RAND(),0,$B$9*0.3)) -> 0.997377 | J18: =ROUND(G18*H18*I18,0) -> 67 | K18: =$B$8 -> 3 | L18: =ROUND(J18*K18,2) -> 202.37
A19: 2026-09-01 | B19: 1 | C19: phase_1_user_growth | D19: =$B$5 -> 3 | E19: =$B$6 -> 5 | F19: =ROUND('MAU'!$F25*D19,0) -> 4779 | G19: =ROUND(F19*E19,0) -> 23895 | H19: =$B$7 -> 0.003 | I19: =MAX(0.8,1+_xlfn.NORM.INV(RAND(),0,$B$9*0.3)) -> 1.019541 | J19: =ROUND(G19*H19*I19,0) -> 73 | K19: =$B$8 -> 3 | L19: =ROUND(J19*K19,2) -> 219.26
A20: 2026-10-01 | B20: 1 | C20: phase_1_user_growth | D20: =$B$5 -> 3 | E20: =$B$6 -> 5 | F20: =ROUND('MAU'!$F26*D20,0) -> 5472 | G20: =ROUND(F20*E20,0) -> 27360 | H20: =$B$7 -> 0.003 | I20: =MAX(0.8,1+_xlfn.NORM.INV(RAND(),0,$B$9*0.3)) -> 1.014384 | J20: =ROUND(G20*H20*I20,0) -> 83 | K20: =$B$8 -> 3 | L20: =ROUND(J20*K20,2) -> 249.78
A21: 2026-11-01 | B21: 1 | C21: phase_1_user_growth | D21: =$B$5 -> 3 | E21: =$B$6 -> 5 | F21: =ROUND('MAU'!$F27*D21,0) -> 8073 | G21: =ROUND(F21*E21,0) -> 40365 | H21: =$B$7 -> 0.003 | I21: =MAX(0.8,1+_xlfn.NORM.INV(RAND(),0,$B$9*0.3)) -> 1.005834 | J21: =ROUND(G21*H21*I21,0) -> 122 | K21: =$B$8 -> 3 | L21: =ROUND(J21*K21,2) -> 365.4
A22: 2026-12-01 | B22: 1 | C22: phase_1_user_growth | D22: =$B$5 -> 3 | E22: =$B$6 -> 5 | F22: =ROUND('MAU'!$F28*D22,0) -> 14994 | G22: =ROUND(F22*E22,0) -> 74970 | H22: =$B$7 -> 0.003 | I22: =MAX(0.8,1+_xlfn.NORM.INV(RAND(),0,$B$9*0.3)) -> 0.989488 | J22: =ROUND(G22*H22*I22,0) -> 223 | K22: =$B$8 -> 3 | L22: =ROUND(J22*K22,2) -> 667.64
A23: 2027-01-01 | B23: 1 | C23: phase_1_user_growth | D23: =$B$5 -> 3 | E23: =$B$6 -> 5 | F23: =ROUND('MAU'!$F29*D23,0) -> 9180 | G23: =ROUND(F23*E23,0) -> 45900 | H23: =$B$7 -> 0.003 | I23: =MAX(0.8,1+_xlfn.NORM.INV(RAND(),0,$B$9*0.3)) -> 1.008456 | J23: =ROUND(G23*H23*I23,0) -> 139 | K23: =$B$8 -> 3 | L23: =ROUND(J23*K23,2) -> 416.59
A24: 2027-02-01 | B24: 1 | C24: phase_1_user_growth | D24: =$B$5 -> 3 | E24: =$B$6 -> 5 | F24: =ROUND('MAU'!$F30*D24,0) -> 9762 | G24: =ROUND(F24*E24,0) -> 48810 | H24: =$B$7 -> 0.003 | I24: =MAX(0.8,1+_xlfn.NORM.INV(RAND(),0,$B$9*0.3)) -> 0.981041 | J24: =ROUND(G24*H24*I24,0) -> 144 | K24: =$B$8 -> 3 | L24: =ROUND(J24*K24,2) -> 430.96
... A48: 2029-02-01 | B48: 3 | C48: phase_3_projection | D48: =$B$5 -> 3 | E48: =$B$6 -> 5 | F48: =ROUND('MAU'!$F54*D48,0) -> 32364 | G48: =ROUND(F48*E48,0) -> 161820 | H48: =$B$7 -> 0.003 | I48: =MAX(0.8,1+_xlfn.NORM.INV(RAND(),0,$B$9*0.3)) -> 0.976729 | J48: =ROUND(G48*H48*I48,0) -> 474 | K48: =$B$8 -> 3 | L48: =ROUND(J48*K48,2) -> 1422.49
